Workbook

Sheet 00 Cover
C2: NEXT plc
C3: Three-statement financial model
C5: Author | D5: Obinna Okey-Udeji
C6: Model completed | D6: 46273
C7: Financial information through | D7: 46239
C8: Forecast period | D8: FY2027E–FY2031E
C9: Scenario | D9: Base Case
C10: Currency and units | D10: GBP, £m except where stated
C11: Version | D11: 1.0 — public model
C12: Accounting checks | D12: ='04 Audit & Sources'!E6 -> PASS
C14: Purpose: explain NEXT’s historical performance and a five-year base-case forecast through linked income, cash-flow and balance-sheet statements.
C16: Sources: January 2024–2026 annual reports and results, plus the 5 August 2026 Q2 trading statement. Later disclosures have not been incorporated.
C18: 1. Review the key forecast drivers
C19: 2. Read the three financial statements
C20: 3. Trace the supporting schedules
C21: 4. Review checks, assumptions and sources
C23: Update blue input cells, recalculate, then review the Audit status. Formulas use black text on the same sheet and green for links; outputs on this Cover are dark. Pale amber identifies editable forecast inputs.
C26: Financial development
C27: £m unless stated | D27: FY2023A | E27: FY2024A | F27: FY2025A | G27: FY2026A | H27: FY2027E | I27: FY2028E | J27: FY2029E | K27: FY2030E | L27: FY2031E
C28: Revenue | D28: ='02 Model'!D8 -> 5034 | E28: ='02 Model'!E8 -> 5491 | F28: ='02 Model'!F8 -> 6118.1 | G28: ='02 Model'!G8 -> 6901.3 | H28: ='02 Model'!H8 -> 7265.621 | I28: ='02 Model'!I8 -> 7701.5583 | J28: ='02 Model'!J8 -> 8125.144 | K28: ='02 Model'!K8 -> 8531.4012 | L28: ='02 Model'!L8 -> 8915.3142
C29: Statutory revenue growth | D29: ="n.a." -> n.a. | E29: ='02 Model'!E8/'02 Model'!D8-1 -> 0.090782678 | F29: ='02 Model'!F8/'02 Model'!E8-1 -> 0.11420506 | G29: ='02 Model'!G8/'02 Model'!F8-1 -> 0.1280136 | H29: ='02 Model'!H8/'02 Model'!G8-1 -> 0.052790199 | I29: ='02 Model'!I8/'02 Model'!H8-1 -> 0.06 | J29: ='02 Model'!J8/'02 Model'!I8-1 -> 0.055 | K29: ='02 Model'!K8/'02 Model'!J8-1 -> 0.05 | L29: ='02 Model'!L8/'02 Model'!K8-1 -> 0.045
C30: Operating margin | D30: ='02 Model'!D24/'02 Model'!D8 -> 0.18702821 | E30: ='02 Model'!E24/'02 Model'!E8 -> 0.17991258 | F30: ='02 Model'!F24/'02 Model'!F8 -> 0.17577352 | G30: ='02 Model'!G24/'02 Model'!G8 -> 0.18529842 | H30: ='02 Model'!H24/'02 Model'!H8 -> 0.18334839 | I30: ='02 Model'!I24/'02 Model'!I8 -> 0.18437695 | J30: ='02 Model'!J24/'02 Model'!J8 -> 0.18490003 | K30: ='02 Model'!K24/'02 Model'!K8 -> 0.18491761 | L30: ='02 Model'!L24/'02 Model'!L8 -> 0.18542967
C31: PBT margin | D31: ='02 Model'!D28/'02 Model'!D8 -> 0.17268574 | E31: ='02 Model'!E28/'02 Model'!E8 -> 0.18499363 | F31: ='02 Model'!F28/'02 Model'!F8 -> 0.16132459 | G31: ='02 Model'!G28/'02 Model'!G8 -> 0.17280802 | H31: ='02 Model'!H28/'02 Model'!H8 -> 0.17175807 | I31: ='02 Model'!I28/'02 Model'!I8 -> 0.17445065 | J31: ='02 Model'!J28/'02 Model'!J8 -> 0.17563424 | K31: ='02 Model'!K28/'02 Model'!K8 -> 0.17633022 | L31: ='02 Model'!L28/'02 Model'!L8 -> 0.17743493
C32: Profit before tax | D32: ='02 Model'!D28 -> 869.3 | E32: ='02 Model'!E28 -> 1015.8 | F32: ='02 Model'!F28 -> 987 | G32: ='02 Model'!G28 -> 1192.6 | H32: ='02 Model'!H28 -> 1247.929 | I32: ='02 Model'!I28 -> 1343.5418 | J32: ='02 Model'!J28 -> 1427.0535 | K32: ='02 Model'!K28 -> 1504.3439 | L32: ='02 Model'!L28 -> 1581.8882
C33: Total cash capex | D33: =-'02 Model'!D102-'02 Model'!D106 -> 246.1 | E33: =-'02 Model'!E102-'02 Model'!E106 -> 188.2 | F33: =-'02 Model'!F102-'02 Model'!F106 -> 157.5 | G33: =-'02 Model'!G102-'02 Model'!G106 -> 171.2 | H33: =-'02 Model'!H102-'02 Model'!H106 -> 237 | I33: =-'02 Model'!I102-'02 Model'!I106 -> 252 | J33: =-'02 Model'!J102-'02 Model'!J106 -> 227 | K33: =-'02 Model'!K102-'02 Model'!K106 -> 289 | L33: =-'02 Model'!L102-'02 Model'!L106 -> 300
C34: Free cash flow after capex, interest and leases | D34: ='02 Model'!D99+'02 Model'!D102+'02 Model'!D106+'02 Model'!D122+'02 Model'!D123 -> 321.5 | E34: ='02 Model'!E99+'02 Model'!E102+'02 Model'!E106+'02 Model'!E122+'02 Model'!E123 -> 696.8 | F34: ='02 Model'!F99+'02 Model'!F102+'02 Model'!F106+'02 Model'!F122+'02 Model'!F123 -> 718.5 | G34: ='02 Model'!G99+'02 Model'!G102+'02 Model'!G106+'02 Model'!G122+'02 Model'!G123 -> 800.9 | H34: ='02 Model'!H99+'02 Model'!H102+'02 Model'!H106+'02 Model'!H122+'02 Model'!H123 -> 1042.9482 | I34: ='02 Model'!I99+'02 Model'!I102+'02 Model'!I106+'02 Model'!I122+'02 Model'!I123 -> 864.89327 | J34: ='02 Model'!J99+'02 Model'!J102+'02 Model'!J106+'02 Model'!J122+'02 Model'!J123 -> 1118.2097 | K34: ='02 Model'!K99+'02 Model'!K102+'02 Model'!K106+'02 Model'!K122+'02 Model'!K123 -> 971.15077 | L34: ='02 Model'!L99+'02 Model'!L102+'02 Model'!L106+'02 Model'!L122+'02 Model'!L123 -> 1193.1848
C35: Net debt excluding leases (cash equivalents) | D35: ='03 Schedules'!D161 -> 788 | E35: ='03 Schedules'!E161 -> 690.7 | F35: ='03 Schedules'!F161 -> 654 | G35: ='03 Schedules'!G161 -> 712.7 | H35: ='03 Schedules'!H161 -> 620.25185 | I35: ='03 Schedules'!I161 -> 632 | J35: ='03 Schedules'!J161 -> 632 | K35: ='03 Schedules'!K161 -> 632 | L35: ='03 Schedules'!L161 -> 632
C36: Ordinary dividends paid | D36: =-'02 Model'!D129 -> 237.4 | E36: =-'02 Model'!E129 -> 248.3 | F36: =-'02 Model'!F129 -> 257.8 | G36: =-'02 Model'!G129 -> 286.5 | H36: =-'02 Model'!H129 -> 318 | I36: =-'02 Model'!I129 -> 340.4 | J36: =-'02 Model'!J129 -> 374.1 | K36: =-'02 Model'!K129 -> 396.1 | L36: =-'02 Model'!L129 -> 417.2
C37: Non-ordinary shareholder returns | D37: =-'02 Model'!D114-'02 Model'!D128 -> 228.5 | E37: =-'02 Model'!E114-'02 Model'!E128 -> 177.3 | F37: =-'02 Model'!F114-'02 Model'!F128 -> 360.2 | G37: =-'02 Model'!G114-'02 Model'!G128 -> 552.9 | H37: =-'02 Model'!H114-'02 Model'!H128 -> 524 | I37: =-'02 Model'!I114-'02 Model'!I128 -> 461.48248 | J37: =-'02 Model'!J114-'02 Model'!J128 -> 665.86848 | K37: =-'02 Model'!K114-'02 Model'!K128 -> 493.36318 | L37: =-'02 Model'!L114-'02 Model'!L128 -> 690.84942
C39: Free cash flow here means operating cash after tax, cash capex, borrowing interest and lease payments. It excludes acquisitions and shareholder returns. Net debt excludes lease liabilities and uses cash equivalents.
C41: FY2027 reported revenue growth includes the effect of removing FY2026’s 53rd week; the forecast input is 7% growth on the comparable 52-week base.
N44: Period | O44: Operating margin | P44: PBT margin
N45: =D27 -> FY2023A | O45: =D30 -> 0.18702821 | P45: =D31 -> 0.17268574
N46: =E27 -> FY2024A | O46: =E30 -> 0.17991258 | P46: =E31 -> 0.18499363
N47: =F27 -> FY2025A | O47: =F30 -> 0.17577352 | P47: =F31 -> 0.16132459
N48: =G27 -> FY2026A | O48: =G30 -> 0.18529842 | P48: =G31 -> 0.17280802
N49: =H27 -> FY2027E | O49: =H30 -> 0.18334839 | P49: =H31 -> 0.17175807
N50: =I27 -> FY2028E | O50: =I30 -> 0.18437695 | P50: =I31 -> 0.17445065
N51: =J27 -> FY2029E | O51: =J30 -> 0.18490003 | P51: =J31 -> 0.17563424
N52: =K27 -> FY2030E | O52: =K30 -> 0.18491761 | P52: =K31 -> 0.17633022
N53: =L27 -> FY2031E | O53: =L30 -> 0.18542967 | P53: =L31 -> 0.17743493
C60: Interpretation: growth moderates while modest cost efficiencies and lower finance-cost intensity support margins. Cash generation and shareholder returns vary with average-balance working-capital formulas.
C62: Educational portfolio project by Obinna Okey-Udeji. Independently prepared and not affiliated with or endorsed by NEXT plc. This model is not investment advice.
C64: Version history: 1.0, 8 September 2026 — five-sheet public presentation, linked audit framework and archived detailed change history. Accepted statement forecasts retained.
C66: Model assumptions include refinancing, minimum cash, annual depreciation and lease inputs, fixed cash dividends and temporary minor-balance roll-forwards. Review the notes in Audit & Sources before interpreting the forecast.

Sheet 01 Assumptions
C2: Forecast assumptions
C4: Return to Cover
C5: £m except percentages, days and per-share data
D6: FY2023A | E6: FY2024A | F6: FY2025A | G6: FY2026A | H6: FY2027E | I6: FY2028E | J6: FY2029E | K6: FY2030E | L6: FY2031E
C8: Operating performance
C9: Revenue growth | H9: 0.07 | I9: 0.06 | J9: 0.055 | K9: 0.05 | L9: 0.045 | N9: A005
C10: Cost of sales / Revenue | H10: 0.557 | I10: 0.558 | J10: 0.559 | K10: 0.56 | L10: 0.56 | N10: A006
C11: Distribution costs / Revenue | H11: 0.148 | I11: 0.147 | J11: 0.1465 | K11: 0.146 | L11: 0.146 | N11: A007
C12: Administrative expenses / Revenue | H12: 0.11 | I12: 0.109 | J12: 0.108 | K12: 0.1075 | L12: 0.107 | N12: A008
C13: Receivables impairment expense (£m) | H13: 20 | I13: 21 | J13: 22 | K13: 23 | L13: 24 | N13: A085
C14: Share of associates and JVs (£m) | H14: 8 | I14: 8.5 | J14: 9 | K14: 9.5 | L14: 10 | N14: A086
C16: Working capital and customer credit
C17: Inventory days | H17: 86 | I17: 86 | J17: 86 | K17: 86 | L17: 86 | N17: A070
C18: Payables days | H18: 33 | I18: 33 | J18: 33 | K18: 33 | L18: 33 | N18: A021
C19: Customer-credit-book growth | H19: n.a. | I19: 0.02 | J19: 0.02 | K19: 0.02 | L19: 0.02 | N19: A088
C20: Prepayments / Revenue | H20: 0.011 | I20: 0.011 | J20: 0.011 | K20: 0.011 | L20: 0.011 | N20: A014
C21: Other creditors & accruals / Revenue | H21: 0.072 | I21: 0.072 | J21: 0.072 | K21: 0.072 | L21: 0.072 | N21: A023
C23: CapEx and investment
C24: Total cash capex (£m) | H24: 237 | I24: 252 | J24: 227 | K24: 289 | L24: 300 | N24: A126
C25: Intangible additions (£m) | H25: 29 | I25: 32 | J25: 32 | K25: 32 | L25: 32 | N25: A012
C27: Leases
C28: ROU new lease additions (£m) | H28: 120 | I28: 125 | J28: 130 | K28: 135 | L28: 140 | N28: A062
C29: Lease payments (£m) | H29: 225 | I29: 230 | J29: 235 | K29: 240 | L29: 245 | N29: A035
C30: Lease interest rate | H30: 0.055 | I30: 0.053 | J30: 0.051 | K30: 0.05 | L30: 0.05 | N30: A029
C32: Financing and interest
C33: Minimum balance-sheet cash (£m) | H33: n.a. | I33: 100 | J33: 100 | K33: 100 | L33: 100 | N33: A090
C34: Bank loans & overdrafts — closing balance (£m) | H34: 96 | I34: 96 | J34: 96 | K34: 96 | L34: 96 | N34: A058
C35: bank / RCF / overdraft rate (%) | H35: 0.05 | I35: 0.05 | J35: 0.05 | K35: 0.05 | L35: 0.05 | N35: A079
C36: Cash yield (%) | H36: 0.035 | I36: 0.0325 | J36: 0.03 | K36: 0.03 | L36: 0.03 | N36: A046
C37: Refinancing rate | H37: n.a. | I37: 0.045 | J37: 0.045 | K37: 0.045 | L37: 0.045 | N37: A093
C38: 2028 bond refinancing proceeds (£m) | H38: 0 | I38: 0 | J38: 300 | K38: 0 | L38: 0 | N38: A092
C39: RCF renewal / replacement assumed (1 = yes) | H39: 1 | I39: 1 | J39: 1 | K39: 1 | L39: 1 | N39: A095
C41: Tax
C42: Tax rate | H42: 0.25 | I42: 0.25 | J42: 0.25 | K42: 0.25 | L42: 0.25 | N42: A009
C44: Dividends, buybacks and capital allocation
C45: Economic dividend payout | H45: 0.36 | I45: 0.36 | J45: 0.36 | K45: 0.36 | L45: 0.36 | N45: A089
C46: Cash dividends paid (£m) | H46: 318 | I46: 340.4 | J46: 374.1 | K46: 396.1 | L46: 417.2 | N46: A087
C47: Average buyback price (£/share) | H47: n.a. | I47: 140 | J47: 147 | K47: 154 | L47: 162 | N47: A091
C48: NCI dividend payout | H48: n.a. | I48: 0.7 | J48: 0.7 | K48: 0.7 | L48: 0.7 | N48: A096
C49: ERR condition assumed satisfied (1 = yes) | H49: 1 | I49: 1 | J49: 1 | K49: 1 | L49: 1 | N49: A121
C52: 29 key drivers. Supporting inputs, calculated results and zero-event or temporary assumptions are located in the relevant section of 03 Schedules.
C54: Blue numbers are inputs. Green formulas link to another sheet. FY2028–FY2031 assumptions are independent model judgements unless a source explicitly identifies contractual terms or disclosed investment plans.
C56: Open supporting inputs and schedules

Sheet 02 Model
C2: Financial statements
C4: Return to Cover
C5: £m. Liabilities and cash outflows are negative.
D6: FY2023A | E6: FY2024A | F6: FY2025A | G6: FY2026A | H6: FY2027E | I6: FY2028E | J6: FY2029E | K6: FY2030E | L6: FY2031E
C7: INCOME STATEMENT | N7: Earnings calculation
C8: Revenue | D8: 5034 | E8: 5491 | F8: 6118.1 | G8: 6901.3 | H8: ='03 Schedules'!H362 -> 7265.621 | I8: ='03 Schedules'!I362 -> 7701.5583 | J8: ='03 Schedules'!J362 -> 8125.144 | K8: ='03 Schedules'!K362 -> 8531.4012 | L8: ='03 Schedules'!L362 -> 8915.3142 | N8: H8
C9: Revenue growth | E9: =E8/D8-1 -> 0.090782678 | F9: =F8/E8-1 -> 0.11420506 | G9: =G8/F8-1 -> 0.1280136 | H9: ='03 Schedules'!H363 -> 0.07 | I9: ='03 Schedules'!I363 -> 0.06 | J9: ='03 Schedules'!J363 -> 0.055 | K9: ='03 Schedules'!K363 -> 0.05 | L9: ='03 Schedules'!L363 -> 0.045 | N9: H9
C10: Cost of sales | D10: -2827.7 | E10: -3034.5 | F10: -3456.5 | G10: -3847.5 | H10: ='03 Schedules'!H364 -> -4046.9509 | I10: ='03 Schedules'!I364 -> -4297.4695 | J10: ='03 Schedules'!J364 -> -4541.9555 | K10: ='03 Schedules'!K364 -> -4777.5847 | L10: ='03 Schedules'!L364 -> -4992.576 | N10: H10
C11: Cost of sales as % of Revenue | D11: =-D10/D8 -> 0.5617203 | E11: =-E10/E8 -> 0.55263158 | F11: =-F10/F8 -> 0.56496298 | G11: =-G10/G8 -> 0.55750366 | H11: ='03 Schedules'!H365 -> 0.557 | I11: ='03 Schedules'!I365 -> 0.558 | J11: ='03 Schedules'!J365 -> 0.559 | K11: ='03 Schedules'!K365 -> 0.56 | L11: ='03 Schedules'!L365 -> 0.56 | N11: H11
C12: Impairment losses on customer and other receivables | D12: -31 | E12: -36 | F12: -19.4 | G12: -7.1 | H12: ='03 Schedules'!H366 -> -20 | I12: ='03 Schedules'!I366 -> -21 | J12: ='03 Schedules'!J366 -> -22 | K12: ='03 Schedules'!K366 -> -23 | L12: ='03 Schedules'!L366 -> -24 | N12: H12
C13: Gross profit | D13: =SUM(D8,D10,D12) -> 2175.3 | E13: =SUM(E8,E10,E12) -> 2420.5 | F13: =SUM(F8,F10,F12) -> 2642.2 | G13: =SUM(G8,G10,G12) -> 3046.7 | H13: ='03 Schedules'!H367 -> 3198.6701 | I13: ='03 Schedules'!I367 -> 3383.0888 | J13: ='03 Schedules'!J367 -> 3561.1885 | K13: ='03 Schedules'!K367 -> 3730.8165 | L13: ='03 Schedules'!L367 -> 3898.7383 | N13: H13
C14: Gross margin | D14: =D13/D8 -> 0.43212157 | E14: =E13/E8 -> 0.44081224 | F14: =F13/F8 -> 0.4318661 | G14: =G13/G8 -> 0.44146755 | H14: ='03 Schedules'!H368 -> 0.44024731 | I14: ='03 Schedules'!I368 -> 0.43927328 | J14: ='03 Schedules'!J368 -> 0.43829236 | K14: ='03 Schedules'!K368 -> 0.43730408 | L14: ='03 Schedules'!L368 -> 0.437308 | N14: H14
C15: Distribution costs | D15: -750 | E15: -794.1 | F15: -878.8 | G15: -1027.1 | H15: ='03 Schedules'!H369 -> -1075.3119 | I15: ='03 Schedules'!I369 -> -1132.1291 | J15: ='03 Schedules'!J369 -> -1190.3336 | K15: ='03 Schedules'!K369 -> -1245.5846 | L15: ='03 Schedules'!L369 -> -1301.6359 | N15: H15
C16: Distribution costs as % of Revenue | D16: =-D15/D8 -> 0.14898689 | E16: =-E15/E8 -> 0.14461847 | F16: =-F15/F8 -> 0.14363937 | G16: =-G15/G8 -> 0.14882703 | H16: ='03 Schedules'!H370 -> 0.148 | I16: ='03 Schedules'!I370 -> 0.147 | J16: ='03 Schedules'!J370 -> 0.1465 | K16: ='03 Schedules'!K370 -> 0.146 | L16: ='03 Schedules'!L370 -> 0.146 | N16: H16
C17: Administrative expenses | D17: -481.8 | E17: -657.7 | F17: -670.6 | G17: -742.4 | H17: ='03 Schedules'!H371 -> -799.21831 | I17: ='03 Schedules'!I371 -> -839.46985 | J17: ='03 Schedules'!J371 -> -877.51555 | K17: ='03 Schedules'!K371 -> -917.12562 | L17: ='03 Schedules'!L371 -> -953.93862 | N17: H17
C18: Administrative expenses as % of Revenue | D18: =-D17/D8 -> 0.095709178 | E18: =-E17/E8 -> 0.11977782 | F18: =-F17/F8 -> 0.10960919 | G18: =-G17/G8 -> 0.10757394 | H18: ='03 Schedules'!H372 -> 0.11 | I18: ='03 Schedules'!I372 -> 0.109 | J18: ='03 Schedules'!J372 -> 0.108 | K18: ='03 Schedules'!K372 -> 0.1075 | L18: ='03 Schedules'!L372 -> 0.107 | N18: H18
C19: Other gains / (losses) | D19: -16.3 | E19: 12.3 | F19: 3.4 | G19: -3.4 | H19: ='03 Schedules'!H373 -> 0 | I19: ='03 Schedules'!I373 -> 0 | J19: ='03 Schedules'!J373 -> 0 | K19: ='03 Schedules'!K373 -> 0 | L19: ='03 Schedules'!L373 -> 0 | N19: H19
C20: Trading profit | D20: =SUM(D13,D15,D17,D19) -> 927.2 | E20: =SUM(E13,E15,E17,E19) -> 981 | F20: =SUM(F13,F15,F17,F19) -> 1096.2 | G20: =SUM(G13,G15,G17,G19) -> 1273.8 | H20: ='03 Schedules'!H374 -> 1324.1399 | I20: ='03 Schedules'!I374 -> 1411.4898 | J20: ='03 Schedules'!J374 -> 1493.3393 | K20: ='03 Schedules'!K374 -> 1568.1063 | L20: ='03 Schedules'!L374 -> 1643.1638 | N20: H20
C21: Share of results of associates and joint ventures | D21: 14.3 | E21: 6.9 | F21: 6.7 | G21: 7.9 | H21: ='03 Schedules'!H375 -> 8 | I21: ='03 Schedules'!I375 -> 8.5 | J21: ='03 Schedules'!J375 -> 9 | K21: ='03 Schedules'!K375 -> 9.5 | L21: ='03 Schedules'!L375 -> 10 | N21: H21
C22: Impairment in associates and joint ventures | D22: 0 | E22: 0 | F22: -13 | G22: -2.9 | H22: ='03 Schedules'!H376 -> 0 | I22: ='03 Schedules'!I376 -> 0 | J22: ='03 Schedules'!J376 -> 0 | K22: ='03 Schedules'!K376 -> 0 | L22: ='03 Schedules'!L376 -> 0 | N22: H22
C23: Exceptional items — curtailment loss | D23: 0 | E23: 0 | F23: -14.5 | G23: 0 | H23: ='03 Schedules'!H377 -> 0 | I23: ='03 Schedules'!I377 -> 0 | J23: ='03 Schedules'!J377 -> 0 | K23: ='03 Schedules'!K377 -> 0 | L23: ='03 Schedules'!L377 -> 0 | N23: H23
C24: Operating profit | D24: =SUM(D20:D23) -> 941.5 | E24: =SUM(E20:E23) -> 987.9 | F24: =SUM(F20:F23) -> 1075.4 | G24: =SUM(G20:G23) -> 1278.8 | H24: ='03 Schedules'!H378 -> 1332.1399 | I24: ='03 Schedules'!I378 -> 1419.9898 | J24: ='03 Schedules'!J378 -> 1502.3393 | K24: ='03 Schedules'!K378 -> 1577.6063 | L24: ='03 Schedules'!L378 -> 1653.1638 | N24: H24
C25: Gain on Reiss transaction — exceptional item | D25: 0 | E25: 108.6 | F25: 0 | G25: 0 | H25: ='03 Schedules'!H379 -> 0 | I25: ='03 Schedules'!I379 -> 0 | J25: ='03 Schedules'!J379 -> 0 | K25: ='03 Schedules'!K379 -> 0 | L25: ='03 Schedules'!L379 -> 0 | N25: H25
C26: Finance income | D26: 5.7 | E26: 6.8 | F26: 8.2 | G26: 11 | H26: ='03 Schedules'!H380 -> 5.367 | I26: ='03 Schedules'!I380 -> 5.731815 | J26: ='03 Schedules'!J380 -> 5.2 | K26: ='03 Schedules'!K380 -> 5.3 | L26: ='03 Schedules'!L380 -> 5.4 | N26: H26
C27: Finance costs | D27: -77.9 | E27: -87.5 | F27: -96.6 | G27: -97.2 | H27: ='03 Schedules'!H381 -> -89.577867 | I27: ='03 Schedules'!I381 -> -82.179817 | J27: ='03 Schedules'!J381 -> -80.48586 | K27: ='03 Schedules'!K381 -> -78.56244 | L27: ='03 Schedules'!L381 -> -76.675562 | N27: H27
C28: Profit before tax | D28: =SUM(D24:D27) -> 869.3 | E28: =SUM(E24:E27) -> 1015.8 | F28: =SUM(F24:F27) -> 987 | G28: =SUM(G24:G27) -> 1192.6 | H28: ='03 Schedules'!H382 -> 1247.929 | I28: ='03 Schedules'!I382 -> 1343.5418 | J28: ='03 Schedules'!J382 -> 1427.0535 | K28: ='03 Schedules'!K382 -> 1504.3439 | L28: ='03 Schedules'!L382 -> 1581.8882 | N28: H28
C29: Taxation | D29: -158.6 | E29: -215.3 | F29: -243.8 | G29: -294.6 | H29: ='03 Schedules'!H383 -> -311.98225 | I29: ='03 Schedules'!I383 -> -335.88546 | J29: ='03 Schedules'!J383 -> -356.76337 | K29: ='03 Schedules'!K383 -> -376.08597 | L29: ='03 Schedules'!L383 -> -395.47205 | N29: H29
C30: Net income | D30: =SUM(D28:D29) -> 710.7 | E30: =SUM(E28:E29) -> 800.5 | F30: =SUM(F28:F29) -> 743.2 | G30: =SUM(G28:G29) -> 898 | H30: ='03 Schedules'!H384 -> 935.94676 | I30: ='03 Schedules'!I384 -> 1007.6564 | J30: ='03 Schedules'!J384 -> 1070.2901 | K30: ='03 Schedules'!K384 -> 1128.2579 | L30: ='03 Schedules'!L384 -> 1186.4161 | N30: H30
C33: BALANCE SHEET | N33: Supporting schedules
C35: ASSETS
C36: Non-current assets
C37: Property, plant and equipment | D37: 644.8 | E37: 687.5 | F37: 686.4 | G37: 667.7 | H37: ='03 Schedules'!H23 -> 755.7 | I37: ='03 Schedules'!I23 -> 847.7 | J37: ='03 Schedules'!J23 -> 902.7 | K37: ='03 Schedules'!K23 -> 1004.7 | L37: ='03 Schedules'!L23 -> 1102.7 | N37: H37
C38: Intangible assets | D38: 137.1 | E38: 757.2 | F38: 735.4 | G38: 713.7 | H38: ='03 Schedules'!H44 -> 684.7 | I38: ='03 Schedules'!I44 -> 656.7 | J38: ='03 Schedules'!J44 -> 626.7 | K38: ='03 Schedules'!K44 -> 594.7 | L38: ='03 Schedules'!L44 -> 560.7 | N38: H38
C39: Right-of-use assets | D39: 662 | E39: 734.6 | F39: 737.3 | G39: 733.1 | H39: ='03 Schedules'!H74 -> 719.1 | I39: ='03 Schedules'!I74 -> 708.1 | J39: ='03 Schedules'!J74 -> 700.1 | K39: ='03 Schedules'!K74 -> 695.1 | L39: ='03 Schedules'!L74 -> 693.1 | N39: H39
C40: Associates, joint ventures and other investments | D40: 114.6 | E40: 38 | F40: 32.7 | G40: 35.2 | H40: ='03 Schedules'!H50 -> 43.2 | I40: ='03 Schedules'!I50 -> 51.7 | J40: ='03 Schedules'!J50 -> 60.7 | K40: ='03 Schedules'!K50 -> 70.2 | L40: ='03 Schedules'!L50 -> 80.2 | N40: H40
C41: Defined benefit pension asset | D41: 157.5 | E41: 59.3 | F41: 30.8 | G41: 23 | H41: ='03 Schedules'!H255 -> 23 | I41: ='03 Schedules'!I255 -> 23 | J41: ='03 Schedules'!J255 -> 23 | K41: ='03 Schedules'!K255 -> 23 | L41: ='03 Schedules'!L255 -> 23 | N41: H41
C42: Other non-current assets (financial / deferred tax) | D42: 33.3 | E42: 0 | F42: 0 | G42: 0.2 | H42: ='03 Schedules'!H256 -> 0.2 | I42: ='03 Schedules'!I256 -> 0.2 | J42: ='03 Schedules'!J256 -> 0.2 | K42: ='03 Schedules'!K256 -> 0.2 | L42: ='03 Schedules'!L256 -> 0.2 | N42: H42
C43: Total non-current assets | D43: =SUM(D37:D42) -> 1749.3 | E43: =SUM(E37:E42) -> 2276.6 | F43: =SUM(F37:F42) -> 2222.6 | G43: =SUM(G37:G42) -> 2172.9 | H43: =SUM(H37,H38,H39,H40,'03 Schedules'!H255,'03 Schedules'!H256) -> 2225.9 | I43: =SUM(I37,I38,I39,I40,'03 Schedules'!I255,'03 Schedules'!I256) -> 2287.4 | J43: =SUM(J37,J38,J39,J40,'03 Schedules'!J255,'03 Schedules'!J256) -> 2313.4 | K43: =SUM(K37,K38,K39,K40,'03 Schedules'!K255,'03 Schedules'!K256) -> 2387.9 | L43: =SUM(L37,L38,L39,L40,'03 Schedules'!L255,'03 Schedules'!L256) -> 2459.9 | N43: H43
C45: Current assets
C46: Inventories | D46: 662.2 | E46: 769 | F46: 865.2 | G46: 949.5 | H46: ='03 Schedules'!H107 -> 957.55631 | I46: ='03 Schedules'!I107 -> 1067.5526 | J46: ='03 Schedules'!J107 -> 1072.7661 | K46: ='03 Schedules'!K107 -> 1178.5888 | L46: ='03 Schedules'!L107 -> 1174.0771 | N46: H46
C47: Customer and other receivables | D47: 1425.5 | E47: 1452.8 | F47: 1508.4 | G47: 1660.6 | H47: ='03 Schedules'!H118 -> 1647.9218 | I47: ='03 Schedules'!I118 -> 1691.7371 | J47: ='03 Schedules'!J118 -> 1736.957 | K47: ='03 Schedules'!K118 -> 1781.5374 | L47: ='03 Schedules'!L118 -> 1825.4343 | N47: H47
C48: Right of return asset | D48: 32.7 | E48: 30.7 | F48: 34.8 | G48: 29.7 | H48: ='03 Schedules'!H96 -> 32 | I48: ='03 Schedules'!I96 -> 34 | J48: ='03 Schedules'!J96 -> 36 | K48: ='03 Schedules'!K96 -> 38 | L48: ='03 Schedules'!L96 -> 40 | N48: H48
C49: Other financial assets — current | D49: 9.1 | E49: 6.9 | F49: 31.8 | G49: 6.4 | H49: ='03 Schedules'!H257 -> 6.4 | I49: ='03 Schedules'!I257 -> 6.4 | J49: ='03 Schedules'!J257 -> 6.4 | K49: ='03 Schedules'!K257 -> 6.4 | L49: ='03 Schedules'!L257 -> 6.4 | N49: H49
C50: Current tax assets | D50: 0 | E50: 0 | F50: 9.3 | G50: 0 | H50: ='03 Schedules'!H258 -> 0 | I50: ='03 Schedules'!I258 -> 0 | J50: ='03 Schedules'!J258 -> 0 | K50: ='03 Schedules'!K258 -> 0 | L50: ='03 Schedules'!L258 -> 0 | N50: H50
C51: Cash and short-term deposits | D51: 105 | E51: 188.3 | F51: 200.4 | G51: 96.2 | H51: =H137+(G51-G137) -> 111.74815 | I51: =I137+'03 Schedules'!I152 -> 100 | J51: =J137+'03 Schedules'!J152 -> 100 | K51: =K137+'03 Schedules'!K152 -> 100 | L51: =L137+'03 Schedules'!L152 -> 100 | N51: H51
C52: Total current assets | D52: =SUM(D46:D51) -> 2234.5 | E52: =SUM(E46:E51) -> 2447.7 | F52: =SUM(F46:F51) -> 2649.9 | G52: =SUM(G46:G51) -> 2742.4 | H52: =SUM(H46,H47,H48,'03 Schedules'!H257,'03 Schedules'!H258,H51) -> 2755.6263 | I52: =SUM(I46,I47,I48,'03 Schedules'!I257,'03 Schedules'!I258,I51) -> 2899.6897 | J52: =SUM(J46,J47,J48,'03 Schedules'!J257,'03 Schedules'!J258,J51) -> 2952.1231 | K52: =SUM(K46,K47,K48,'03 Schedules'!K257,'03 Schedules'!K258,K51) -> 3104.5262 | L52: =SUM(L46,L47,L48,'03 Schedules'!L257,'03 Schedules'!L258,L51) -> 3145.9114 | N52: H52
C53: TOTAL ASSETS | D53: =SUM(D43,D52) -> 3983.8 | E53: =SUM(E43,E52) -> 4724.3 | F53: =SUM(F43,F52) -> 4872.5 | G53: =SUM(G43,G52) -> 4915.3 | H53: =H43+H52 -> 4981.5263 | I53: =I43+I52 -> 5187.0897 | J53: =J43+J52 -> 5265.5231 | K53: =K43+K52 -> 5492.4262 | L53: =L43+L52 -> 5605.8114 | N53: H53
C55: LIABILITIES
C56: Current liabilities
C57: Bank loans and overdrafts | D57: -102.3 | E57: -58.7 | F57: -60.6 | G57: -96 | H57: =-'03 Schedules'!H156 -> -96 | I57: =-'03 Schedules'!I156 -> -96 | J57: =-'03 Schedules'!J156 -> -96 | K57: =-'03 Schedules'!K156 -> -96 | L57: =-'03 Schedules'!L156 -> -96 | N57: H57
C58: Corporate bonds — current | D58: 0 | E58: 0 | F58: -250 | G58: -112.9 | H58: ='03 Schedules'!H142 -> 0 | I58: =-'03 Schedules'!I157 -> -300 | J58: =-'03 Schedules'!J157 -> 0 | K58: =-'03 Schedules'!K157 -> 0 | L58: =-'03 Schedules'!L157 -> -300 | N58: H58
C59: Trade payables and other payables | D59: -791.1 | E59: -991.8 | F59: -1076.7 | G59: -1132.4 | H59: =-'03 Schedules'!H130 -> -1226.1083 | I59: =-'03 Schedules'!I130 -> -1269.152 | J59: =-'03 Schedules'!J130 -> -1364.55 | K59: =-'03 Schedules'!K130 -> -1403.0835 | L59: =-'03 Schedules'!L130 -> -1490.8618 | N59: H59
C60: Lease liabilities — current | D60: -146.2 | E60: -167.8 | F60: -170.8 | G60: -168.1 | H60: =-'03 Schedules'!H87 -> -163.26055 | I60: =-'03 Schedules'!I87 -> -157.96936 | J60: =-'03 Schedules'!J87 -> -152.0818 | K60: =-'03 Schedules'!K87 -> -145.74189 | L60: =-'03 Schedules'!L87 -> -139.08498 | N60: H60
C61: Other financial liabilities — current | D61: -40.8 | E61: -18.8 | F61: -8.3 | G61: -35.5 | H61: ='03 Schedules'!H259 -> -35.5 | I61: ='03 Schedules'!I259 -> -35.5 | J61: ='03 Schedules'!J259 -> -35.5 | K61: ='03 Schedules'!K259 -> -35.5 | L61: ='03 Schedules'!L259 -> -35.5 | N61: H61
C62: Current tax liabilities | D62: -12.9 | E62: -8.6 | F62: 0 | G62: -9.2 | H62: ='03 Schedules'!H260 -> -40.882255 | I62: ='03 Schedules'!I260 -> -40.882255 | J62: ='03 Schedules'!J260 -> -40.882255 | K62: ='03 Schedules'!K260 -> -40.882255 | L62: ='03 Schedules'!L260 -> -40.882255 | N62: H62
C63: Total current liabilities | D63: =SUM(D57:D62) -> -1093.3 | E63: =SUM(E57:E62) -> -1245.7 | F63: =SUM(F57:F62) -> -1566.4 | G63: =SUM(G57:G62) -> -1554.1 | H63: =SUM(H57,H58,H59,H60,'03 Schedules'!H259,'03 Schedules'!H260) -> -1561.7511 | I63: =SUM(I57,I58,I59,I60,'03 Schedules'!I259,'03 Schedules'!I260) -> -1899.5036 | J63: =SUM(J57,J58,J59,J60,'03 Schedules'!J259,'03 Schedules'!J260) -> -1689.014 | K63: =SUM(K57,K58,K59,K60,'03 Schedules'!K259,'03 Schedules'!K260) -> -1721.2076 | L63: =SUM(L57,L58,L59,L60,'03 Schedules'!L259,'03 Schedules'!L260) -> -2102.329 | N63: H63
C65: Non-current liabilities
C66: Borrowings — non-current | D66: -790.7 | E66: -820.3 | F66: -543.8 | G66: -600 | H66: =-'03 Schedules'!H158 -> -600 | I66: =-'03 Schedules'!I158 -> -300 | J66: =-'03 Schedules'!J158 -> -600 | K66: =-'03 Schedules'!K158 -> -600 | L66: =-'03 Schedules'!L158 -> -300 | N66: H66
C67: Provisions | D67: -33.8 | E67: -52.4 | F67: -55.7 | G67: -58.5 | H67: ='03 Schedules'!H261 -> -58.5 | I67: ='03 Schedules'!I261 -> -58.5 | J67: ='03 Schedules'!J261 -> -58.5 | K67: ='03 Schedules'!K261 -> -58.5 | L67: ='03 Schedules'!L261 -> -58.5 | N67: H67
C68: Lease liabilities — non-current | D68: -877.1 | E68: -869.9 | F68: -843.6 | G68: -831.7 | H68: =-'03 Schedules'!H88 -> -808.52845 | I68: =-'03 Schedules'!I88 -> -782.32446 | J68: =-'03 Schedules'!J88 -> -753.167 | K68: =-'03 Schedules'!K88 -> -721.76935 | L68: =-'03 Schedules'!L88 -> -688.80182 | N68: H68
C69: Other financial liabilities — non-current | D69: -9.5 | E69: -37.4 | F69: -39.1 | G69: -38.2 | H69: ='03 Schedules'!H262 -> -38.2 | I69: ='03 Schedules'!I262 -> -38.2 | J69: ='03 Schedules'!J262 -> -38.2 | K69: ='03 Schedules'!K262 -> -38.2 | L69: ='03 Schedules'!L262 -> -38.2 | N69: H69
C70: Other payables — non-current | D70: -14.3 | E70: -11.7 | F70: -11.5 | G70: -17.6 | H70: ='03 Schedules'!H263 -> -17.6 | I70: ='03 Schedules'!I263 -> -17.6 | J70: ='03 Schedules'!J263 -> -17.6 | K70: ='03 Schedules'!K263 -> -17.6 | L70: ='03 Schedules'!L263 -> -17.6 | N70: H70
C71: Deferred tax liabilities | D71: 0 | E71: -48.1 | F71: -58.1 | G71: -34.7 | H71: ='03 Schedules'!H264 -> -35 | I71: ='03 Schedules'!I264 -> -35 | J71: ='03 Schedules'!J264 -> -35 | K71: ='03 Schedules'!K264 -> -35 | L71: ='03 Schedules'!L264 -> -35 | N71: H71
C72: Total non-current liabilities | D72: =SUM(D66:D71) -> -1725.4 | E72: =SUM(E66:E71) -> -1839.8 | F72: =SUM(F66:F71) -> -1551.8 | G72: =SUM(G66:G71) -> -1580.7 | H72: =SUM(H66,'03 Schedules'!H261,H68,'03 Schedules'!H262,'03 Schedules'!H263,'03 Schedules'!H264) -> -1557.8284 | I72: =SUM(I66,'03 Schedules'!I261,I68,'03 Schedules'!I262,'03 Schedules'!I263,'03 Schedules'!I264) -> -1231.6245 | J72: =SUM(J66,'03 Schedules'!J261,J68,'03 Schedules'!J262,'03 Schedules'!J263,'03 Schedules'!J264) -> -1502.467 | K72: =SUM(K66,'03 Schedules'!K261,K68,'03 Schedules'!K262,'03 Schedules'!K263,'03 Schedules'!K264) -> -1471.0694 | L72: =SUM(L66,'03 Schedules'!L261,L68,'03 Schedules'!L262,'03 Schedules'!L263,'03 Schedules'!L264) -> -1138.1018 | N72: H72
C73: TOTAL LIABILITIES | D73: =SUM(D63,D72) -> -2818.7 | E73: =SUM(E63,E72) -> -3085.5 | F73: =SUM(F63,F72) -> -3118.2 | G73: =SUM(G63,G72) -> -3134.8 | H73: =H63+H72 -> -3119.5795 | I73: =I63+I72 -> -3131.128 | J73: =J63+J72 -> -3191.481 | K73: =K63+K72 -> -3192.277 | L73: =L63+L72 -> -3240.4308 | N73: H73
C75: NET ASSETS | D75: =SUM(D53,D73) -> 1165.1 | E75: =SUM(E53,E73) -> 1638.8 | F75: =SUM(F53,F73) -> 1754.3 | G75: =SUM(G53,G73) -> 1780.5 | H75: =H53+H73 -> 1861.9468 | I75: =I53+I73 -> 2055.9617 | J75: =J53+J73 -> 2074.0421 | K75: =K53+K73 -> 2300.1493 | L75: =L53+L73 -> 2365.3806 | N75: H75
C77: EQUITY
C78: Share capital | D78: 12.9 | E78: 12.7 | F78: 12.4 | G78: 12.3 | H78: ='03 Schedules'!H232 -> 11.9 | I78: ='03 Schedules'!I232 -> 11.57037 | J78: ='03 Schedules'!J232 -> 11.117398 | K78: ='03 Schedules'!K232 -> 10.797032 | L78: ='03 Schedules'!L232 -> 10.370582 | N78: H78
C79: Share premium | D79: 0.9 | E79: 54.2 | F79: 54.2 | G79: 54.2 | H79: ='03 Schedules'!H265 -> 54.2 | I79: ='03 Schedules'!I265 -> 54.2 | J79: ='03 Schedules'!J265 -> 54.2 | K79: ='03 Schedules'!K265 -> 54.2 | L79: ='03 Schedules'!L265 -> 54.2 | N79: H79
C80: Capital redemption reserve | D80: 17 | E80: 17.3 | F80: 17.6 | G80: 458.5 | H80: ='03 Schedules'!H238 -> 458.9 | I80: ='03 Schedules'!I238 -> 459.22963 | J80: ='03 Schedules'!J238 -> 459.6826 | K80: ='03 Schedules'!K238 -> 460.00297 | L80: ='03 Schedules'!L238 -> 460.42942 | N80: H80
C81: ESOT reserve | D81: -396.7 | E81: -387.3 | F81: -427.7 | G81: -442.4 | H81: ='03 Schedules'!H266 -> -470.4 | I81: ='03 Schedules'!I266 -> -499.4 | J81: ='03 Schedules'!J266 -> -529.4 | K81: ='03 Schedules'!K266 -> -560.4 | L81: ='03 Schedules'!L266 -> -592.4 | N81: H81
C82: Cash flow hedge reserve | D82: -11.3 | E82: -4.7 | F82: 19.1 | G82: -16.1 | H82: ='03 Schedules'!H267 -> -16.1 | I82: ='03 Schedules'!I267 -> -16.1 | J82: ='03 Schedules'!J267 -> -16.1 | K82: ='03 Schedules'!K267 -> -16.1 | L82: ='03 Schedules'!L267 -> -16.1 | N82: H82
C83: Cost of hedging reserve | D83: 0.4 | E83: -0.3 | F83: -0.2 | G83: -1 | H83: ='03 Schedules'!H268 -> -1 | I83: ='03 Schedules'!I268 -> -1 | J83: ='03 Schedules'!J268 -> -1 | K83: ='03 Schedules'!K268 -> -1 | L83: ='03 Schedules'!L268 -> -1 | N83: H83
C84: Foreign currency translation reserve | D84: -3.7 | E84: -7.5 | F84: -9.7 | G84: -7.3 | H84: ='03 Schedules'!H269 -> -7.3 | I84: ='03 Schedules'!I269 -> -7.3 | J84: ='03 Schedules'!J269 -> -7.3 | K84: ='03 Schedules'!K269 -> -7.3 | L84: ='03 Schedules'!L269 -> -7.3 | N84: H84
C85: Other reserves | D85: -1443.8 | E85: -1443.8 | F85: -1448.9 | G85: -1889.7 | H85: ='03 Schedules'!H270 -> -1889.7 | I85: ='03 Schedules'!I270 -> -1889.7 | J85: ='03 Schedules'!J270 -> -1889.7 | K85: ='03 Schedules'!K270 -> -1889.7 | L85: ='03 Schedules'!L270 -> -1889.7 | N85: H85
C86: Retained earnings | D86: 2984.8 | E86: 3271.3 | F86: 3419.5 | G86: 3494 | H86: ='03 Schedules'!H253 -> 3601.6513 | I86: ='03 Schedules'!I253 -> 3821.341 | J86: ='03 Schedules'!J253 -> 3865.8895 | K86: ='03 Schedules'!K253 -> 4119.2734 | L86: ='03 Schedules'!L253 -> 4212.5895 | N86: H86
C87: Equity attributable to owners of parent | D87: =SUM(D78:D86) -> 1160.5 | E87: =SUM(E78:E86) -> 1511.9 | F87: =SUM(F78:F86) -> 1636.3 | G87: =SUM(G78:G86) -> 1662.5 | H87: =SUM(H78,'03 Schedules'!H265,H80,'03 Schedules'!H266,'03 Schedules'!H267,'03 Schedules'!H268,'03 Schedules'!H269,'03 Schedules'!H270,H86) -> 1742.1513 | I87: =SUM(I78,'03 Schedules'!I265,I80,'03 Schedules'!I266,'03 Schedules'!I267,'03 Schedules'!I268,'03 Schedules'!I269,'03 Schedules'!I270,I86) -> 1932.841 | J87: =SUM(J78,'03 Schedules'!J265,J80,'03 Schedules'!J266,'03 Schedules'!J267,'03 Schedules'!J268,'03 Schedules'!J269,'03 Schedules'!J270,J86) -> 1947.3895 | K87: =SUM(K78,'03 Schedules'!K265,K80,'03 Schedules'!K266,'03 Schedules'!K267,'03 Schedules'!K268,'03 Schedules'!K269,'03 Schedules'!K270,K86) -> 2169.7734 | L87: =SUM(L78,'03 Schedules'!L265,L80,'03 Schedules'!L266,'03 Schedules'!L267,'03 Schedules'!L268,'03 Schedules'!L269,'03 Schedules'!L270,L86) -> 2231.0895 | N87: H87
C88: Non-controlling interests | D88: 4.6 | E88: 126.9 | F88: 118 | G88: 118 | H88: ='03 Schedules'!H271 -> 119.79541 | I88: ='03 Schedules'!I271 -> 123.12068 | J88: ='03 Schedules'!J271 -> 126.65264 | K88: ='03 Schedules'!K271 -> 130.37589 | L88: ='03 Schedules'!L271 -> 134.29106 | N88: H88
C89: TOTAL EQUITY | D89: =SUM(D87,D88) -> 1165.1 | E89: =SUM(E87,E88) -> 1638.8 | F89: =SUM(F87,F88) -> 1754.3 | G89: =SUM(G87,G88) -> 1780.5 | H89: =H87+'03 Schedules'!H271 -> 1861.9468 | I89: =I87+'03 Schedules'!I271 -> 2055.9617 | J89: =J87+'03 Schedules'!J271 -> 2074.0421 | K89: =K87+'03 Schedules'!K271 -> 2300.1493 | L89: =L87+'03 Schedules'!L271 -> 2365.3806 | N89: H89
C91: Balance-sheet difference | D91: =ROUND(D53+D73-D89,1) -> 0 | E91: =ROUND(E53+E73-E89,1) -> 0 | F91: =ROUND(F53+F73-F89,1) -> 0 | G91: =ROUND(G53+G73-G89,1) -> 0 | H91: =H53+H73-H89 -> 0 | I91: =I53+I73-I89 -> 0 | J91: =J53+J73-J89 -> 0 | K91: =K53+K73-K89 -> 0 | L91: =L53+L73-L89 -> 0
C94: CASH-FLOW STATEMENT | N94: Operating cash build
C95: Fiscal year | D95: FY2023A | E95: FY2024A | F95: FY2025A | G95: FY2026A | H95: FY2027E | I95: FY2028E | J95: FY2029E | K95: FY2030E | L95: FY2031E
C96: CASH FLOW FROM OPERATING ACTIVITIES
C97: Cash generated from operations | D97: 950.3 | E97: 1313.6 | F97: 1376.5 | G97: 1466.7 | H97: ='03 Schedules'!H360 -> 1804.537 | I97: ='03 Schedules'!I360 -> 1697.4537 | J97: ='03 Schedules'!J360 -> 1952.504 | K97: ='03 Schedules'!K360 -> 1891.5367 | L97: ='03 Schedules'!L360 -> 2147.9569 | N97: H97
C98: Corporation taxes paid | D98: -151.5 | E98: -193.3 | F98: -242.6 | G98: -233.1 | H98: =-'03 Schedules'!H337 -> -265 | I98: =-'03 Schedules'!I337 -> -319.88546 | J98: =-'03 Schedules'!J337 -> -339.76337 | K98: =-'03 Schedules'!K337 -> -358.08597 | L98: =-'03 Schedules'!L337 -> -376.47205 | N98: H98
C99: Net cash from operating activities | D99: 798.8 | E99: 1120.3 | F99: 1133.9 | G99: 1233.6 | H99: =SUM(H97:H98) -> 1539.537 | I99: =SUM(I97:I98) -> 1377.5683 | J99: =SUM(J97:J98) -> 1612.7406 | K99: =SUM(K97:K98) -> 1533.4508 | L99: =SUM(L97:L98) -> 1771.4848 | N99: H99
C101: CASH FLOW FROM INVESTING ACTIVITIES
C102: Payments to acquire property, plant and equipment | D102: -205.1 | E102: -137 | F102: -129.3 | G102: -135.4 | H102: =-'03 Schedules'!H20 -> -208 | I102: =-'03 Schedules'!I20 -> -220 | J102: =-'03 Schedules'!J20 -> -195 | K102: =-'03 Schedules'!K20 -> -257 | L102: =-'03 Schedules'!L20 -> -268 | N102: H102
C103: Proceeds from sale of property, plant and equipment | D103: 0 | E103: 2 | F103: 2.6 | G103: 0.4 | H103: ='03 Schedules'!H15 -> 0 | I103: ='03 Schedules'!I15 -> 0 | J103: ='03 Schedules'!J15 -> 0 | K103: ='03 Schedules'!K15 -> 0 | L103: ='03 Schedules'!L15 -> 0 | N103: H103
C104: Proceeds from sale of held-for-sale assets | D104: 0 | E104: 0 | F104: 0 | G104: 55.7 | H104: ='03 Schedules'!H16 -> 0 | I104: ='03 Schedules'!I16 -> 0 | J104: ='03 Schedules'!J16 -> 0 | K104: ='03 Schedules'!K16 -> 0 | L104: ='03 Schedules'!L16 -> 0 | N104: H104
C105: Proceeds from sale and leaseback transactions | D105: 41.7 | E105: 3.3 | F105: 0 | G105: 0 | H105: ='03 Schedules'!H17 -> 0 | I105: ='03 Schedules'!I17 -> 0 | J105: ='03 Schedules'!J17 -> 0 | K105: ='03 Schedules'!K17 -> 0 | L105: ='03 Schedules'!L17 -> 0 | N105: H105
C106: Purchase of intangible assets | D106: -41 | E106: -51.2 | F106: -28.2 | G106: -35.8 | H106: =-'03 Schedules'!H41 -> -29 | I106: =-'03 Schedules'!I41 -> -32 | J106: =-'03 Schedules'!J41 -> -32 | K106: =-'03 Schedules'!K41 -> -32 | L106: =-'03 Schedules'!L41 -> -32 | N106: H106
C107: Amounts (loaned to) / repaid by associates and JVs | D107: 11.3 | E107: 0 | F107: -0.9 | G107: -4.8 | H107: ='03 Schedules'!H34 -> 0 | I107: ='03 Schedules'!I34 -> 0 | J107: ='03 Schedules'!J34 -> 0 | K107: ='03 Schedules'!K34 -> 0 | L107: ='03 Schedules'!L34 -> 0 | N107: H107
C108: Investment in subsidiaries | D108: -28.8 | E108: -153.2 | F108: -24.2 | G108: 0 | H108: =-'03 Schedules'!H35 -> 0 | I108: =-'03 Schedules'!I35 -> 0 | J108: =-'03 Schedules'!J35 -> 0 | K108: =-'03 Schedules'!K35 -> 0 | L108: =-'03 Schedules'!L35 -> 0 | N108: H108
C109: Investment in associates and joint ventures | D109: -64.7 | E109: -0.9 | F109: -1.2 | G109: 0 | H109: =-'03 Schedules'!H36 -> 0 | I109: =-'03 Schedules'!I36 -> 0 | J109: =-'03 Schedules'!J36 -> 0 | K109: =-'03 Schedules'!K36 -> 0 | L109: =-'03 Schedules'!L36 -> 0 | N109: H109
C110: Other investing activities | D110: 15.2 | E110: 2.6 | F110: 0 | G110: 0 | H110: ='03 Schedules'!H37 -> 0 | I110: ='03 Schedules'!I37 -> 0 | J110: ='03 Schedules'!J37 -> 0 | K110: ='03 Schedules'!K37 -> 0 | L110: ='03 Schedules'!L37 -> 0 | N110: H110
C111: Net cash used in investing activities | D111: -271.4 | E111: -334.4 | F111: -181.2 | G111: -119.9 | H111: =SUM(H102:H110) -> -237 | I111: =SUM(I102:I110) -> -252 | J111: =SUM(J102:J110) -> -227 | K111: =SUM(K102:K110) -> -289 | L111: =SUM(L102:L110) -> -300 | N111: H111
C113: CASH FLOW FROM FINANCING ACTIVITIES
C114: Repurchase of own shares | D114: -228.5 | E114: -177.3 | F114: -360.2 | G114: -131.4 | H114: =-'03 Schedules'!H301 -> -524 | I114: =-'03 Schedules'!I321 -> -461.48248 | J114: =-'03 Schedules'!J321 -> -665.86848 | K114: =-'03 Schedules'!K321 -> -493.36318 | L114: =-'03 Schedules'!L321 -> -690.84942 | N114: H114
C115: Purchase of shares by ESOT | D115: -124 | E115: -116.3 | F115: -126.8 | G115: -169 | H115: =-'03 Schedules'!H209 -> -158 | I115: =-'03 Schedules'!I209 -> -165 | J115: =-'03 Schedules'!J209 -> -172 | K115: =-'03 Schedules'!K209 -> -180 | L115: =-'03 Schedules'!L209 -> -188 | N115: H115
...

Sheet 03 Schedules
C2: Supporting schedules
C4: Return to Cover
C5: £m except percentages, days and per-share data
D6: FY2023A | E6: FY2024A | F6: FY2025A | G6: FY2026A | H6: FY2027E | I6: FY2028E | J6: FY2029E | K6: FY2030E | L6: FY2031E
C9: 1. PP&E and depreciation | N9: Next section
C10: PP&E depreciation (£m) | H10: -120 | I10: -128 | J10: -140 | K10: -155 | L10: -170 | N10: Supporting schedule input · A010
C11: PP&E disposals/other movements (£m) | H11: 0 | I11: 0 | J11: 0 | K11: 0 | L11: 0 | N11: Zero-event assumption · A011
C12: PP&E additions / CapEx (£m) | H12: ='01 Assumptions'!H24-'01 Assumptions'!H25 -> 208 | I12: ='01 Assumptions'!I24-'01 Assumptions'!I25 -> 220 | J12: ='01 Assumptions'!J24-'01 Assumptions'!J25 -> 195 | K12: ='01 Assumptions'!K24-'01 Assumptions'!K25 -> 257 | L12: ='01 Assumptions'!L24-'01 Assumptions'!L25 -> 268 | N12: Key visible driver · A013
C13: PP&E loss/(profit) on disposal (m) | H13: 0 | I13: 0 | J13: 0 | K13: 0 | L13: 0 | N13: Zero-event assumption · A049
C14: PP&E impairment charge (m) | H14: 0 | I14: 0 | J14: 0 | K14: 0 | L14: 0 | N14: Zero-event assumption · A054
C15: PP&E sale proceeds (£m) | H15: 0 | I15: 0 | J15: 0 | K15: 0 | L15: 0 | N15: Zero-event assumption · A104
C16: Held-for-sale asset proceeds (£m) | H16: 0 | I16: 0 | J16: 0 | K16: 0 | L16: 0 | N16: Zero-event assumption · A105
C17: Sale-and-leaseback proceeds (£m) | H17: 0 | I17: 0 | J17: 0 | K17: 0 | L17: 0 | N17: Zero-event assumption · A106
C19: Opening PP&E | D19: 601.1 | E19: 644.8 | F19: 687.5 | G19: 686.4 | H19: =G23 -> 667.7 | I19: =H23 -> 755.7 | J19: =I23 -> 847.7 | K19: =J23 -> 902.7 | L19: =K23 -> 1004.7
C20: PP&E additions / CapEx | D20: 207.1 | E20: 160.9 | F20: 122.9 | G20: 139.6 | H20: =H12 -> 208 | I20: =I12 -> 220 | J20: =J12 -> 195 | K20: =K12 -> 257 | L20: =L12 -> 268
C21: Depreciation | D21: -100.5 | E21: -94.9 | F21: -114.5 | G21: -116.8 | H21: =H10 -> -120 | I21: =I10 -> -128 | J21: =J10 -> -140 | K21: =K10 -> -155 | L21: =L10 -> -170
C22: Disposals / transfers / other | D22: -62.9 | E22: -23.3 | F22: -9.5 | G22: -41.5 | H22: =H11 -> 0 | I22: =I11 -> 0 | J22: =J11 -> 0 | K22: =K11 -> 0 | L22: =L11 -> 0
C23: Closing PP&E | D23: 644.8 | E23: 687.5 | F23: 686.4 | G23: 667.7 | H23: =SUM(H19:H22) -> 755.7 | I23: =SUM(I19:I22) -> 847.7 | J23: =SUM(J19:J22) -> 902.7 | K23: =SUM(K19:K22) -> 1004.7 | L23: =SUM(L19:L22) -> 1102.7
C28: 2. Intangibles and investments | N28: Next section
C29: Intangible amortisation (£m) | H29: -58 | I29: -60 | J29: -62 | K29: -64 | L29: -66 | N29: Supporting schedule input · A015
C30: Intangible disposal P&L adjustment (m) | H30: 0 | I30: 0 | J30: 0 | K30: 0 | L30: 0 | N30: Zero-event assumption · A052
C31: Intangible impairment (m) | H31: 0 | I31: 0 | J31: 0 | K31: 0 | L31: 0 | N31: Zero-event assumption · A053
C32: Intangible acquisitions / disposals / other (£m) | H32: 0 | I32: 0 | J32: 0 | K32: 0 | L32: 0 | N32: Zero-event assumption · A061
C33: Associates/JVs — new investment / dividends / other (£m) | H33: 0 | I33: 0 | J33: 0 | K33: 0 | L33: 0 | N33: Zero-event assumption · A067
C34: Loans to / from associates and JVs (£m) | H34: 0 | I34: 0 | J34: 0 | K34: 0 | L34: 0 | N34: Zero-event assumption · A107
C35: Investment in subsidiaries (£m) | H35: 0 | I35: 0 | J35: 0 | K35: 0 | L35: 0 | N35: Zero-event assumption · A108
C36: Investment in associates and JVs (£m) | H36: 0 | I36: 0 | J36: 0 | K36: 0 | L36: 0 | N36: Zero-event assumption · A109
C37: Other investing activities (£m) | H37: 0 | I37: 0 | J37: 0 | K37: 0 | L37: 0 | N37: Zero-event assumption · A110
C38: Amounts due from associates/JVs (m) | H38: 20 | I38: 20 | J38: 20 | K38: 20 | L38: 20 | N38: Temporary assumption · A016
C40: Opening intangible assets | D40: 79.3 | E40: 137.1 | F40: 757.2 | G40: 735.4 | H40: =G44 -> 713.7 | I40: =H44 -> 684.7 | J40: =I44 -> 656.7 | K40: =J44 -> 626.7 | L40: =K44 -> 594.7
C41: Intangible additions | D41: 41 | E41: 51.2 | F41: 28.2 | G41: 36.8 | H41: ='01 Assumptions'!H25 -> 29 | I41: ='01 Assumptions'!I25 -> 32 | J41: ='01 Assumptions'!J25 -> 32 | K41: ='01 Assumptions'!K25 -> 32 | L41: ='01 Assumptions'!L25 -> 32
C42: Amortisation | D42: -11.9 | E42: -36.2 | F42: -52.4 | G42: -54.8 | H42: =H29 -> -58 | I42: =I29 -> -60 | J42: =J29 -> -62 | K42: =K29 -> -64 | L42: =L29 -> -66
C43: Acquisitions / disposals / other movements | D43: 28.7 | E43: 605.1 | F43: 2.4 | G43: -3.7 | H43: =H32 -> 0 | I43: =I32 -> 0 | J43: =J32 -> 0 | K43: =K32 -> 0 | L43: =L32 -> 0
C44: Closing intangible assets | D44: 137.1 | E44: 757.2 | F44: 735.4 | G44: 713.7 | H44: =SUM(H40:H43) -> 684.7 | I44: =SUM(I40:I43) -> 656.7 | J44: =SUM(J40:J43) -> 626.7 | K44: =SUM(K40:K43) -> 594.7 | L44: =SUM(L40:L43) -> 560.7
C46: Opening associates/JVs & other investments | D46: 46.2 | E46: 114.6 | F46: 38 | G46: 32.7 | H46: =G50 -> 35.2 | I46: =H50 -> 43.2 | J46: =I50 -> 51.7 | K46: =J50 -> 60.7 | L46: =K50 -> 70.2
C47: Share of results | D47: 14.3 | E47: 6.9 | F47: 6.7 | G47: 7.9 | H47: =H375 -> 8 | I47: =I375 -> 8.5 | J47: =J375 -> 9 | K47: =K375 -> 9.5 | L47: =L375 -> 10
C48: Impairment in associates/JVs | D48: 0 | E48: 0 | F48: -13 | G48: -2.9 | H48: =H376 -> 0 | I48: =I376 -> 0 | J48: =J376 -> 0 | K48: =K376 -> 0 | L48: =L376 -> 0
C49: New investment / dividends / other | D49: 54.1 | E49: -83.5 | F49: 1 | G49: -2.5 | H49: =H33 -> 0 | I49: =I33 -> 0 | J49: =J33 -> 0 | K49: =K33 -> 0 | L49: =L33 -> 0
C50: Closing associates/JVs & other investments | D50: 114.6 | E50: 38 | F50: 32.7 | G50: 35.2 | H50: =SUM(H46:H49) -> 43.2 | I50: =SUM(I46:I49) -> 51.7 | J50: =SUM(J46:J49) -> 60.7 | K50: =SUM(K46:K49) -> 70.2 | L50: =SUM(L46:L49) -> 80.2
C55: 3. Right-of-use assets and lease liabilities | N55: Next section
C56: Lease liabilities arising from acquisitions (£m) | H56: 0 | I56: 0 | J56: 0 | K56: 0 | L56: 0 | N56: Zero-event assumption · A028
C57: Lease liability disposals (£m) | H57: 8 | I57: 8 | J57: 8 | K57: 8 | L57: 8 | N57: Supporting schedule input · A030
C58: Lease liability FX effect (£m) | H58: 0 | I58: 0 | J58: 0 | K58: 0 | L58: 0 | N58: Zero-event assumption · A031
C59: Current lease liability % of total | H59: 0.168 | I59: 0.168 | J59: 0.168 | K59: 0.168 | L59: 0.168 | N59: Supporting schedule input · A032
C60: ROU modification/disposal P&L adjustment (m) | H60: 0 | I60: 0 | J60: 0 | K60: 0 | L60: 0 | N60: Zero-event assumption · A050
C61: ROU impairment/(reversal) (m) | H61: 0 | I61: 0 | J61: 0 | K61: 0 | L61: 0 | N61: Zero-event assumption · A051
C62: ROU assets arising from acquisitions (£m) | H62: 0 | I62: 0 | J62: 0 | K62: 0 | L62: 0 | N62: Zero-event assumption · A063
C63: ROU lease modifications / amendments (£m) | H63: 30 | I63: 30 | J63: 30 | K63: 30 | L63: 30 | N63: Supporting schedule input · A064
C64: ROU depreciation (£m) | H64: -156 | I64: -158 | J64: -160 | K64: -162 | L64: -164 | N64: Supporting schedule input · A065
C65: ROU disposals / impairment / other (£m) | H65: -8 | I65: -8 | J65: -8 | K65: -8 | L65: -8 | N65: Supporting schedule input · A066
C66: Lease incentives received (£m) | H66: 0 | I66: 0 | J66: 0 | K66: 0 | L66: 0 | N66: Zero-event assumption · A113
C68: Opening ROU assets | D68: 639.1 | E68: 662 | F68: 734.6 | G68: 737.3 | H68: =G74 -> 733.1 | I68: =H74 -> 719.1 | J68: =I74 -> 708.1 | K68: =J74 -> 700.1 | L68: =K74 -> 695.1
C69: New lease additions | D69: 58.2 | E69: 40.2 | F69: 130.8 | G69: 129 | H69: ='01 Assumptions'!H28 -> 120 | I69: ='01 Assumptions'!I28 -> 125 | J69: ='01 Assumptions'!J28 -> 130 | K69: ='01 Assumptions'!K28 -> 135 | L69: ='01 Assumptions'!L28 -> 140
C70: Arising from acquisitions | D70: 0 | E70: 80.5 | F70: 0 | G70: 0 | H70: =H62 -> 0 | I70: =I62 -> 0 | J70: =J62 -> 0 | K70: =K62 -> 0 | L70: =L62 -> 0
C71: Lease modifications / amendments | D71: 41.4 | E71: 68.6 | F71: 33.3 | G71: 30.7 | H71: =H63 -> 30 | I71: =I63 -> 30 | J71: =J63 -> 30 | K71: =K63 -> 30 | L71: =L63 -> 30
C72: ROU depreciation | D72: -107.6 | E72: -117.7 | F72: -144.6 | G72: -153.7 | H72: =H64 -> -156 | I72: =I64 -> -158 | J72: =J64 -> -160 | K72: =K64 -> -162 | L72: =L64 -> -164
C73: Disposals / impairment / other | D73: 30.9 | E73: 0.9 | F73: -16.8 | G73: -10.2 | H73: =H65 -> -8 | I73: =I65 -> -8 | J73: =J65 -> -8 | K73: =K65 -> -8 | L73: =L65 -> -8
C74: Closing ROU assets | D74: 662 | E74: 734.6 | F74: 737.3 | G74: 733.1 | H74: =SUM(H68:H73) -> 719.1 | I74: =SUM(I68:I73) -> 708.1 | J74: =SUM(J68:J73) -> 700.1 | K74: =SUM(K68:K73) -> 695.1 | L74: =SUM(L68:L73) -> 693.1
C76: Opening lease liability | D76: 1057.5 | E76: 1023.3 | F76: 1037.7 | G76: 1014.4 | H76: =-('02 Model'!G60+'02 Model'!G68) -> 999.8 | I76: =H85 -> 971.789 | J76: =I85 -> 940.29382 | K76: =J85 -> 905.2488 | L76: =K85 -> 867.51124
C77: Lease additions | D77: 84.2 | E77: 40.1 | F77: 131.9 | G77: 129.3 | H77: ='01 Assumptions'!H28 -> 120 | I77: ='01 Assumptions'!I28 -> 125 | J77: ='01 Assumptions'!J28 -> 130 | K77: ='01 Assumptions'!K28 -> 135 | L77: ='01 Assumptions'!L28 -> 140
C78: Arising from acquisitions | D78: 0 | E78: 84.7 | F78: 0 | G78: 0 | H78: =H56 -> 0 | I78: =I56 -> 0 | J78: =J56 -> 0 | K78: =K56 -> 0 | L78: =L56 -> 0
C79: Lease modifications / amendments | D79: 41.5 | E79: 52.9 | F79: 32.9 | G79: 31.3 | H79: =H63 -> 30 | I79: =I63 -> 30 | J79: =J63 -> 30 | K79: =K63 -> 30 | L79: =L63 -> 30
C80: Lease interest | D80: 47.3 | E80: 47.9 | F80: 54.8 | G80: 55.6 | H80: =H76*H81 -> 54.989 | I80: =I76*I81 -> 51.504817 | J80: =J76*J81 -> 47.954985 | K80: =K76*K81 -> 45.26244 | L80: =L76*L81 -> 43.375562
C81: Implied lease interest rate | D81: 0.044728132 | E81: 0.046809342 | F81: 0.052809097 | G81: 0.054810726 | H81: ='01 Assumptions'!H30 -> 0.055 | I81: ='01 Assumptions'!I30 -> 0.053 | J81: ='01 Assumptions'!J30 -> 0.051 | K81: ='01 Assumptions'!K30 -> 0.05 | L81: ='01 Assumptions'!L30 -> 0.05
C82: Lease payments | D82: -204.4 | E82: -204 | F82: -219.4 | G82: -223 | H82: =-'01 Assumptions'!H29 -> -225 | I82: =-'01 Assumptions'!I29 -> -230 | J82: =-'01 Assumptions'!J29 -> -235 | K82: =-'01 Assumptions'!K29 -> -240 | L82: =-'01 Assumptions'!L29 -> -245
C83: Disposals | D83: -5.5 | E83: -6.3 | F83: -23.1 | G83: -8 | H83: =-H57 -> -8 | I83: =-I57 -> -8 | J83: =-J57 -> -8 | K83: =-K57 -> -8 | L83: =-L57 -> -8
C84: Foreign exchange movement | D84: 2.7 | E84: -0.9 | F84: -0.4 | G84: 0.2 | H84: =H58 -> 0 | I84: =I58 -> 0 | J84: =J58 -> 0 | K84: =K58 -> 0 | L84: =L58 -> 0
C85: Closing lease liability | D85: 1023.3447 | E85: 1037.7468 | F85: 1014.4528 | G85: 999.85481 | H85: =SUM(H76:H80,H82:H84) -> 971.789 | I85: =SUM(I76:I80,I82:I84) -> 940.29382 | J85: =SUM(J76:J80,J82:J84) -> 905.2488 | K85: =SUM(K76:K80,K82:K84) -> 867.51124 | L85: =SUM(L76:L80,L82:L84) -> 827.8868
C87: Current lease liability | D87: 146.2 | E87: 167.8 | F87: 170.8 | G87: 168.1 | H87: =H85*H59 -> 163.26055 | I87: =I85*I59 -> 157.96936 | J87: =J85*J59 -> 152.0818 | K87: =K85*K59 -> 145.74189 | L87: =L85*L59 -> 139.08498
C88: Non-current lease liability | D88: 877.1 | E88: 869.9 | F88: 843.6 | G88: 831.7 | H88: =H85-H87 -> 808.52845 | I88: =I85-I87 -> 782.32446 | J88: =J85-J87 -> 753.167 | K88: =K85-K87 -> 721.76935 | L88: =L85-L87 -> 688.80182
C89: Current % of total | D89: 0.14286486 | E89: 0.16169647 | F89: 0.16836663 | G89: 0.16812441 | H89: =H59 -> 0.168 | I89: =I59 -> 0.168 | J89: =J59 -> 0.168 | K89: =K59 -> 0.168 | L89: =L59 -> 0.168
C90: Split check | D90: 0 | E90: 0 | F90: 0 | G90: 0 | H90: =H85-H87-H88 -> 0 | I90: =I85-I87-I88 -> 0 | J90: =J85-J87-J88 -> 0 | K90: =K85-K87-K88 -> 0 | L90: =L85-L87-L88 -> 0
C95: 4. Inventory, receivables and payables | N95: Next section
C96: Right of return asset (£m) | H96: 32 | I96: 34 | J96: 36 | K96: 38 | L96: 40 | N96: Supporting schedule input · A017
C97: Other taxation & social security (£m) | H97: 120 | I97: 125 | J97: 130 | K97: 135 | L97: 140 | N97: Supporting schedule input · A022
C98: Share-based payment liability (£m) | H98: 0.2 | I98: 0.2 | J98: 0.2 | K98: 0.2 | L98: 0.2 | N98: Temporary assumption · A024
C99: Deferred gift card revenue / Revenue | H99: 0.017 | I99: 0.017 | J99: 0.017 | K99: 0.017 | L99: 0.017 | N99: Supporting schedule input · A025
C100: Refund liabilities / Revenue | H100: 0.009 | I100: 0.009 | J100: 0.009 | K100: 0.009 | L100: 0.009 | N100: Supporting schedule input · A026
C101: Amounts owed to associates/JVs (£m) | H101: 3 | I101: 3 | J101: 3 | K101: 3 | L101: 3 | N101: Temporary assumption · A027
C102: Other debtors (£m) | H102: 57 | I102: 60 | J102: 64 | K102: 67 | L102: 70 | N102: Temporary assumption · A060
C103: Customer receivables — closing balance forecast (£m) | H103: 1351 | I103: =H103*(1+'01 Assumptions'!I19) -> 1378.02 | J103: =I103*(1+'01 Assumptions'!J19) -> 1405.5804 | K103: =J103*(1+'01 Assumptions'!K19) -> 1433.692 | L103: =K103*(1+'01 Assumptions'!L19) -> 1462.3658 | N103: Calculated output · A071
C104: Other trade receivables (£m) | H104: 140 | I104: 149 | J104: 158 | K104: 167 | L104: 175 | N104: Supporting schedule input · A072
C106: Opening inventory | D106: 633 | E106: 662.2 | F106: 769 | G106: 865.2 | H106: =G107 -> 949.5 | I106: =H107 -> 957.55631 | J106: =I107 -> 1067.5526 | K106: =J107 -> 1072.7661 | L106: =K107 -> 1178.5888
C107: Closing inventory | D107: 662.2 | E107: 769 | F107: 865.2 | G107: 949.5 | H107: =2*H108-H106 -> 957.55631 | I107: =2*I108-I106 -> 1067.5526 | J107: =2*J108-J106 -> 1072.7661 | K107: =2*K108-K106 -> 1178.5888 | L107: =2*L108-L106 -> 1174.0771
C108: Average inventory | D108: 647.6 | E108: 715.6 | F108: 817.1 | G108: 907.35 | H108: =H109*H110/H429 -> 953.52816 | I108: =I109*I110/I429 -> 1012.5545 | J108: =J109*J110/J429 -> 1070.1594 | K108: =K109*K110/K429 -> 1125.6775 | L108: =L109*L110/L429 -> 1176.333
C109: COGS | D109: 2827.7 | E109: 3034.5 | F109: 3456.5 | G109: 3847.5 | H109: =-H364 -> 4046.9509 | I109: =-I364 -> 4297.4695 | J109: =-J364 -> 4541.9555 | K109: =-K364 -> 4777.5847 | L109: =-L364 -> 4992.576
C110: Inventory days | D110: 83.592319 | E110: 86.074806 | F110: 86.284247 | G110: 86.077388 | H110: ='01 Assumptions'!H17 -> 86 | I110: ='01 Assumptions'!I17 -> 86 | J110: ='01 Assumptions'!J17 -> 86 | K110: ='01 Assumptions'!K17 -> 86 | L110: ='01 Assumptions'!L17 -> 86
C112: Opening customer & other receivables | D112: 1280.9 | E112: 1425.5 | F112: 1452.8 | G112: 1508.4 | H112: =G118 -> 1660.6 | I112: =H118 -> 1647.9218 | J112: =I118 -> 1691.7371 | K112: =J118 -> 1736.957 | L112: =K118 -> 1781.5374
C113: Customer receivables | D113: 1254.7 | E113: 1270.4 | F113: 1322.7 | G113: 1368.1 | H113: =H103 -> 1351 | I113: =I103 -> 1378.02 | J113: =J103 -> 1405.5804 | K113: =K103 -> 1433.692 | L113: =L103 -> 1462.3658
C114: Other trade receivables | D114: 42.6 | E114: 62.9 | F114: 46.5 | G114: 139.8 | H114: =H104 -> 140 | I114: =I104 -> 149 | J114: =J104 -> 158 | K114: =K104 -> 167 | L114: =L104 -> 175
C115: Prepayments | D115: 54.9 | E115: 63.6 | F115: 68.3 | G115: 77.4 | H115: =H120*'01 Assumptions'!H20 -> 79.921831 | I115: =I120*'01 Assumptions'!I20 -> 84.717141 | J115: =J120*'01 Assumptions'!J20 -> 89.376584 | K115: =K120*'01 Assumptions'!K20 -> 93.845413 | L115: =L120*'01 Assumptions'!L20 -> 98.068456
C116: Other debtors | D116: 40.7 | E116: 43.8 | F116: 58.7 | G116: 55.4 | H116: =H102 -> 57 | I116: =I102 -> 60 | J116: =J102 -> 64 | K116: =K102 -> 67 | L116: =L102 -> 70
C117: Amounts due from associates/JVs | D117: 32.6 | E117: 12.1 | F117: 12.2 | G117: 19.9 | H117: =H38 -> 20 | I117: =I38 -> 20 | J117: =J38 -> 20 | K117: =K38 -> 20 | L117: =L38 -> 20
C118: Closing customer & other receivables | D118: 1425.5 | E118: 1452.8 | F118: 1508.4 | G118: 1660.6 | H118: =SUM(H113:H117) -> 1647.9218 | I118: =SUM(I113:I117) -> 1691.7371 | J118: =SUM(J113:J117) -> 1736.957 | K118: =SUM(K113:K117) -> 1781.5374 | L118: =SUM(L113:L117) -> 1825.4343
C119: Average customer & other receivables | D119: 1353.2 | E119: 1439.15 | F119: 1480.6 | G119: 1584.5 | H119: =AVERAGE(H112,H118) -> 1654.2609 | I119: =AVERAGE(I112,I118) -> 1669.8295 | J119: =AVERAGE(J112,J118) -> 1714.3471 | K119: =AVERAGE(K112,K118) -> 1759.2472 | L119: =AVERAGE(L112,L118) -> 1803.4859
C120: Revenue | D120: 5034 | E120: 5491 | F120: 6118.1 | G120: 6901.3 | H120: =H362 -> 7265.621 | I120: =I362 -> 7701.5583 | J120: =J362 -> 8125.144 | K120: =K362 -> 8531.4012 | L120: =L362 -> 8915.3142
C121: Receivables days / revenue days | D121: 98.116408 | E121: 95.663768 | F121: 88.331181 | G121: 83.801965 | H121: =H119/H120*H429 -> 83.104422 | I121: =I119/I120*I429 -> 79.13824 | J121: =J119/J120*J429 -> 77.01238 | K121: =K119/K120*K429 -> 75.266092 | L121: =L119/L120*L429 -> 73.836135
C123: Trade payables | D123: 230.1 | E123: 297.1 | F123: 355.8 | G123: 340.9 | H123: =2*H134-H132 -> 390.87742 | I123: =2*I134-I132 -> 386.19926 | J123: =2*J134-J132 -> 435.08584 | K123: =2*K134-K132 -> 428.80618 | L123: =2*L134-L132 -> 473.96098
C124: Amounts owed to associates/JVs | D124: 2.1 | E124: 1.1 | F124: 1.4 | G124: 3.1 | H124: =H101 -> 3 | I124: =I101 -> 3 | J124: =J101 -> 3 | K124: =K101 -> 3 | L124: =L101 -> 3
C125: Refund liabilities | D125: 8.3 | E125: 11.1 | F125: 47.7 | G125: 63 | H125: =H362*H100 -> 65.390589 | I125: =I362*I100 -> 69.314024 | J125: =J362*J100 -> 73.126296 | K125: =K362*K100 -> 76.78261 | L125: =L362*L100 -> 80.237828
...

Sheet 04 Audit & Sources
C2: Audit and sources
C4: Return to Cover
C6: Overall accounting status | E6: =IF(COUNTIFS(I10:I159,"PASS")=150,"PASS","REVIEW") -> PASS
C9: Check | D9: Period | E9: Actual | F9: Expected | G9: Difference | H9: Tolerance | I9: Status | J9: Location / interpretation
C10: Balance sheet | D10: FY2023A | E10: ='02 Model'!D53 -> 3983.8 | F10: =-'02 Model'!D73+'02 Model'!D89 -> 3983.8 | G10: =E10-F10 -> 0 | H10: 0.1 | I10: =IF(COUNT(E10:H10)<4,"UNAVAILABLE",IF(ABS(G10)<=H10,"PASS","FAIL")) -> PASS | J10: 02 Model!D91
C11: Cash-flow closing cash | D11: FY2023A | E11: ='02 Model'!D137 -> 2.7 | F11: =SUM('02 Model'!D134,'02 Model'!D133,'02 Model'!D135,'02 Model'!D136) -> 2.7 | G11: =E11-F11 -> -1.687539e-14 | H11: 0.1 | I11: =IF(COUNT(E11:H11)<4,"UNAVAILABLE",IF(ABS(G11)<=H11,"PASS","FAIL")) -> PASS | J11: 02 Model!D137
C12: Balance sheet | D12: FY2024A | E12: ='02 Model'!E53 -> 4724.3 | F12: =-'02 Model'!E73+'02 Model'!E89 -> 4724.3 | G12: =E12-F12 -> 0 | H12: 0.1 | I12: =IF(COUNT(E12:H12)<4,"UNAVAILABLE",IF(ABS(G12)<=H12,"PASS","FAIL")) -> PASS | J12: 02 Model!E91
C13: Cash-flow closing cash | D13: FY2024A | E13: ='02 Model'!E137 -> 124.3 | F13: =SUM('02 Model'!E134,'02 Model'!E133,'02 Model'!E135,'02 Model'!E136) -> 124.3 | G13: =E13-F13 -> 0 | H13: 0.1 | I13: =IF(COUNT(E13:H13)<4,"UNAVAILABLE",IF(ABS(G13)<=H13,"PASS","FAIL")) -> PASS | J13: 02 Model!E137
C14: Balance sheet | D14: FY2025A | E14: ='02 Model'!F53 -> 4872.5 | F14: =-'02 Model'!F73+'02 Model'!F89 -> 4872.5 | G14: =E14-F14 -> 0 | H14: 0.1 | I14: =IF(COUNT(E14:H14)<4,"UNAVAILABLE",IF(ABS(G14)<=H14,"PASS","FAIL")) -> PASS | J14: 02 Model!F91
C15: Cash-flow closing cash | D15: FY2025A | E15: ='02 Model'!F137 -> 171.3 | F15: =SUM('02 Model'!F134,'02 Model'!F133,'02 Model'!F135,'02 Model'!F136) -> 171.3 | G15: =E15-F15 -> 0 | H15: 0.1 | I15: =IF(COUNT(E15:H15)<4,"UNAVAILABLE",IF(ABS(G15)<=H15,"PASS","FAIL")) -> PASS | J15: 02 Model!F137
C16: Balance sheet | D16: FY2026A | E16: ='02 Model'!G53 -> 4915.3 | F16: =-'02 Model'!G73+'02 Model'!G89 -> 4915.3 | G16: =E16-F16 -> 0 | H16: 0.1 | I16: =IF(COUNT(E16:H16)<4,"UNAVAILABLE",IF(ABS(G16)<=H16,"PASS","FAIL")) -> PASS | J16: 02 Model!G91
C17: Cash-flow closing cash | D17: FY2026A | E17: ='02 Model'!G137 -> 60.2 | F17: =SUM('02 Model'!G134,'02 Model'!G133,'02 Model'!G135,'02 Model'!G136) -> 60.2 | G17: =E17-F17 -> 0 | H17: 0.1 | I17: =IF(COUNT(E17:H17)<4,"UNAVAILABLE",IF(ABS(G17)<=H17,"PASS","FAIL")) -> PASS | J17: 02 Model!G137
C18: Balance sheet | D18: FY2027E | E18: ='02 Model'!H53 -> 4981.5263 | F18: =-'02 Model'!H73+'02 Model'!H89 -> 4981.5263 | G18: =E18-F18 -> 0 | H18: 0.1 | I18: =IF(COUNT(E18:H18)<4,"UNAVAILABLE",IF(ABS(G18)<=H18,"PASS","FAIL")) -> PASS | J18: 02 Model!H91
C19: Cash-flow closing cash | D19: FY2027E | E19: ='02 Model'!H137 -> 75.748155 | F19: =SUM('02 Model'!H134,'02 Model'!H133,'02 Model'!H135,'02 Model'!H136) -> 75.748155 | G19: =E19-F19 -> 0 | H19: 0.1 | I19: =IF(COUNT(E19:H19)<4,"UNAVAILABLE",IF(ABS(G19)<=H19,"PASS","FAIL")) -> PASS | J19: 02 Model!H137
C20: Balance sheet | D20: FY2028E | E20: ='02 Model'!I53 -> 5187.0897 | F20: =-'02 Model'!I73+'02 Model'!I89 -> 5187.0897 | G20: =E20-F20 -> 0 | H20: 0.1 | I20: =IF(COUNT(E20:H20)<4,"UNAVAILABLE",IF(ABS(G20)<=H20,"PASS","FAIL")) -> PASS | J20: 02 Model!I91
C21: Cash-flow closing cash | D21: FY2028E | E21: ='02 Model'!I137 -> 64 | F21: =SUM('02 Model'!I134,'02 Model'!I133,'02 Model'!I135,'02 Model'!I136) -> 64 | G21: =E21-F21 -> 0 | H21: 0.1 | I21: =IF(COUNT(E21:H21)<4,"UNAVAILABLE",IF(ABS(G21)<=H21,"PASS","FAIL")) -> PASS | J21: 02 Model!I137
C22: Balance sheet | D22: FY2029E | E22: ='02 Model'!J53 -> 5265.5231 | F22: =-'02 Model'!J73+'02 Model'!J89 -> 5265.5231 | G22: =E22-F22 -> 0 | H22: 0.1 | I22: =IF(COUNT(E22:H22)<4,"UNAVAILABLE",IF(ABS(G22)<=H22,"PASS","FAIL")) -> PASS | J22: 02 Model!J91
C23: Cash-flow closing cash | D23: FY2029E | E23: ='02 Model'!J137 -> 64 | F23: =SUM('02 Model'!J134,'02 Model'!J133,'02 Model'!J135,'02 Model'!J136) -> 64 | G23: =E23-F23 -> 0 | H23: 0.1 | I23: =IF(COUNT(E23:H23)<4,"UNAVAILABLE",IF(ABS(G23)<=H23,"PASS","FAIL")) -> PASS | J23: 02 Model!J137
C24: Balance sheet | D24: FY2030E | E24: ='02 Model'!K53 -> 5492.4262 | F24: =-'02 Model'!K73+'02 Model'!K89 -> 5492.4262 | G24: =E24-F24 -> 0 | H24: 0.1 | I24: =IF(COUNT(E24:H24)<4,"UNAVAILABLE",IF(ABS(G24)<=H24,"PASS","FAIL")) -> PASS | J24: 02 Model!K91
C25: Cash-flow closing cash | D25: FY2030E | E25: ='02 Model'!K137 -> 64 | F25: =SUM('02 Model'!K134,'02 Model'!K133,'02 Model'!K135,'02 Model'!K136) -> 64 | G25: =E25-F25 -> 0 | H25: 0.1 | I25: =IF(COUNT(E25:H25)<4,"UNAVAILABLE",IF(ABS(G25)<=H25,"PASS","FAIL")) -> PASS | J25: 02 Model!K137
C26: Balance sheet | D26: FY2031E | E26: ='02 Model'!L53 -> 5605.8114 | F26: =-'02 Model'!L73+'02 Model'!L89 -> 5605.8114 | G26: =E26-F26 -> 0 | H26: 0.1 | I26: =IF(COUNT(E26:H26)<4,"UNAVAILABLE",IF(ABS(G26)<=H26,"PASS","FAIL")) -> PASS | J26: 02 Model!L91
C27: Cash-flow closing cash | D27: FY2031E | E27: ='02 Model'!L137 -> 64 | F27: =SUM('02 Model'!L134,'02 Model'!L133,'02 Model'!L135,'02 Model'!L136) -> 64 | G27: =E27-F27 -> 0 | H27: 0.1 | I27: =IF(COUNT(E27:H27)<4,"UNAVAILABLE",IF(ABS(G27)<=H27,"PASS","FAIL")) -> PASS | J27: 02 Model!L137
C28: Closing cash definition bridge | D28: FY2027E | E28: ='02 Model'!H51-'02 Model'!H137 -> 36 | F28: ='02 Model'!G51-'02 Model'!G137 -> 36 | G28: =E28-F28 -> 0 | H28: 0.1 | I28: =IF(COUNT(E28:H28)<4,"UNAVAILABLE",IF(ABS(G28)<=H28,"PASS","FAIL")) -> PASS | J28: Prior-period cash classification difference carried forward.
C29: Gross-debt roll-forward | D29: FY2027E | E29: ='03 Schedules'!H159 -> 696 | F29: ='03 Schedules'!H197 -> 696 | G29: =E29-F29 -> 0 | H29: 0.1 | I29: =IF(COUNT(E29:H29)<4,"UNAVAILABLE",IF(ABS(G29)<=H29,"PASS","FAIL")) -> PASS | J29: Opening gross debt + debt cash receipts / payments.
C30: Debt to balance sheet | D30: FY2027E | E30: ='03 Schedules'!H159 -> 696 | F30: =-SUM('02 Model'!H57:'02 Model'!H58)-'02 Model'!H66 -> 696 | G30: =E30-F30 -> 0 | H30: 0.1 | I30: =IF(COUNT(E30:H30)<4,"UNAVAILABLE",IF(ABS(G30)<=H30,"PASS","FAIL")) -> PASS | J30: Bank debt plus current and non-current bonds.
C31: Finance cost to schedule | D31: FY2027E | E31: =-'02 Model'!H27 -> 89.577867 | F31: ='03 Schedules'!H171+'03 Schedules'!H172+'03 Schedules'!H173 -> 89.577867 | G31: =E31-F31 -> 0 | H31: 0.1 | I31: =IF(COUNT(E31:H31)<4,"UNAVAILABLE",IF(ABS(G31)<=H31,"PASS","FAIL")) -> PASS | J31: Borrowing, lease and other finance costs.
C32: Cash interest consistency | D32: FY2027E | E32: =-'02 Model'!H123 -> 89.577867 | F32: ='03 Schedules'!H171+'03 Schedules'!H172 -> 89.577867 | G32: =E32-F32 -> 0 | H32: 0.1 | I32: =IF(COUNT(E32:H32)<4,"UNAVAILABLE",IF(ABS(G32)<=H32,"PASS","FAIL")) -> PASS | J32: Interest paid reconciles to borrowing and lease interest.
C33: Finance income | D33: FY2027E | E33: ='02 Model'!H26 -> 5.367 | F33: ='03 Schedules'!H168+'03 Schedules'!H169 -> 5.367 | G33: =E33-F33 -> 0 | H33: 0.1 | I33: =IF(COUNT(E33:H33)<4,"UNAVAILABLE",IF(ABS(G33)<=H33,"PASS","FAIL")) -> PASS | J33: Opening cash yield plus other finance income.
C34: Lease liability roll-forward | D34: FY2027E | E34: =-('02 Model'!H60+'02 Model'!H68) -> 971.789 | F34: ='03 Schedules'!H76+'03 Schedules'!H77+'03 Schedules'!H78+'03 Schedules'!H79+'03 Schedules'!H80+'03 Schedules'!H82+'03 Schedules'!H83+'03 Schedules'!H84 -> 971.789 | G34: =E34-F34 -> 0 | H34: 0.1 | I34: =IF(COUNT(E34:H34)<4,"UNAVAILABLE",IF(ABS(G34)<=H34,"PASS","FAIL")) -> PASS | J34: Opening, additions, interest, payments, disposals and FX.
C35: Lease liability split | D35: FY2027E | E35: ='03 Schedules'!H85 -> 971.789 | F35: ='03 Schedules'!H87+'03 Schedules'!H88 -> 971.789 | G35: =E35-F35 -> 0 | H35: 0.1 | I35: =IF(COUNT(E35:H35)<4,"UNAVAILABLE",IF(ABS(G35)<=H35,"PASS","FAIL")) -> PASS | J35: Current plus non-current classification.
C36: PP&E roll-forward | D36: FY2027E | E36: ='02 Model'!H37 -> 755.7 | F36: =SUM('03 Schedules'!H19:H22) -> 755.7 | G36: =E36-F36 -> 0 | H36: 0.1 | I36: =IF(COUNT(E36:H36)<4,"UNAVAILABLE",IF(ABS(G36)<=H36,"PASS","FAIL")) -> PASS | J36: Closing asset equals opening plus scheduled changes.
C37: Intangibles roll-forward | D37: FY2027E | E37: ='02 Model'!H38 -> 684.7 | F37: =SUM('03 Schedules'!H40:H43) -> 684.7 | G37: =E37-F37 -> 0 | H37: 0.1 | I37: =IF(COUNT(E37:H37)<4,"UNAVAILABLE",IF(ABS(G37)<=H37,"PASS","FAIL")) -> PASS | J37: Closing asset equals opening plus scheduled changes.
C38: ROU assets roll-forward | D38: FY2027E | E38: ='02 Model'!H39 -> 719.1 | F38: =SUM('03 Schedules'!H68:H73) -> 719.1 | G38: =E38-F38 -> 0 | H38: 0.1 | I38: =IF(COUNT(E38:H38)<4,"UNAVAILABLE",IF(ABS(G38)<=H38,"PASS","FAIL")) -> PASS | J38: Closing asset equals opening plus scheduled changes.
C39: Associates roll-forward | D39: FY2027E | E39: ='02 Model'!H40 -> 43.2 | F39: =SUM('03 Schedules'!H46:H49) -> 43.2 | G39: =E39-F39 -> 0 | H39: 0.1 | I39: =IF(COUNT(E39:H39)<4,"UNAVAILABLE",IF(ABS(G39)<=H39,"PASS","FAIL")) -> PASS | J39: Closing asset equals opening plus scheduled changes.
C40: Inventory cash reconciliation | D40: FY2027E | E40: ='03 Schedules'!H357 -> -10.356313 | F40: =-('02 Model'!H46-'02 Model'!G46)-('02 Model'!H48-'02 Model'!G48) -> -10.356313 | G40: =E40-F40 -> 0 | H40: 0.1 | I40: =IF(COUNT(E40:H40)<4,"UNAVAILABLE",IF(ABS(G40)<=H40,"PASS","FAIL")) -> PASS | J40: Inventory and right-of-return asset both included.
C41: Receivables cash reconciliation | D41: FY2027E | E41: ='03 Schedules'!H358 -> 12.678169 | F41: ='02 Model'!G47-'02 Model'!H47 -> 12.678169 | G41: =E41-F41 -> 0 | H41: 0.1 | I41: =IF(COUNT(E41:H41)<4,"UNAVAILABLE",IF(ABS(G41)<=H41,"PASS","FAIL")) -> PASS | J41: Credit book and other receivable components.
C42: Payables cash reconciliation | D42: FY2027E | E42: ='03 Schedules'!H359 -> 93.70828 | F42: ='02 Model'!G59-'02 Model'!H59 -> 93.70828 | G42: =E42-F42 -> 0 | H42: 0.1 | I42: =IF(COUNT(E42:H42)<4,"UNAVAILABLE",IF(ABS(G42)<=H42,"PASS","FAIL")) -> PASS | J42: Positive liability growth is a cash source.
C43: Receivables composition | D43: FY2027E | E43: ='02 Model'!H47 -> 1647.9218 | F43: =SUM('03 Schedules'!H113:H117) -> 1647.9218 | G43: =E43-F43 -> 0 | H43: 0.1 | I43: =IF(COUNT(E43:H43)<4,"UNAVAILABLE",IF(ABS(G43)<=H43,"PASS","FAIL")) -> PASS | J43: Sum of the component receivable accounts.
C44: Payables composition | D44: FY2027E | E44: =-'02 Model'!H59 -> 1226.1083 | F44: =SUM('03 Schedules'!H123:H129) -> 1226.1083 | G44: =E44-F44 -> 0 | H44: 0.1 | I44: =IF(COUNT(E44:H44)<4,"UNAVAILABLE",IF(ABS(G44)<=H44,"PASS","FAIL")) -> PASS | J44: Sum of the component payable accounts.
C45: Retained earnings roll-forward | D45: FY2027E | E45: ='02 Model'!H86 -> 3601.6513 | F45: =SUM('03 Schedules'!H241:H252) -> 3601.6513 | G45: =E45-F45 -> 0 | H45: 0.1 | I45: =IF(COUNT(E45:H45)<4,"UNAVAILABLE",IF(ABS(G45)<=H45,"PASS","FAIL")) -> PASS | J45: Owners’ profit, ordinary and special returns, ESOT, equity tax.
C46: Owners and NCI earnings | D46: FY2027E | E46: ='02 Model'!H30 -> 935.94676 | F46: ='03 Schedules'!H242+('02 Model'!H30*'03 Schedules'!H210) -> 935.94676 | G46: =E46-F46 -> 0 | H46: 0.1 | I46: =IF(COUNT(E46:H46)<4,"UNAVAILABLE",IF(ABS(G46)<=H46,"PASS","FAIL")) -> PASS | J46: Owners’ share plus NCI share equals total net income.
C47: NCI roll-forward | D47: FY2027E | E47: ='02 Model'!H88 -> 119.79541 | F47: ='02 Model'!G88+'02 Model'!H30-'03 Schedules'!H242+'02 Model'!H130 -> 119.79541 | G47: =E47-F47 -> -1.1368684e-13 | H47: 0.1 | I47: =IF(COUNT(E47:H47)<4,"UNAVAILABLE",IF(ABS(G47)<=H47,"PASS","FAIL")) -> PASS | J47: NCI opening balance, earnings and dividends.
C48: Total capex | D48: FY2027E | E48: =-'02 Model'!H102-'02 Model'!H106 -> 237 | F48: ='01 Assumptions'!H24 -> 237 | G48: =E48-F48 -> 0 | H48: 0.1 | I48: =IF(COUNT(E48:H48)<4,"UNAVAILABLE",IF(ABS(G48)<=H48,"PASS","FAIL")) -> PASS | J48: PP&E and intangible cash capex equal the approved total.
C49: Dividend cash and equity | D49: FY2027E | E49: ='02 Model'!H129 -> -318 | F49: ='03 Schedules'!H249 -> -318 | G49: =E49-F49 -> 0 | H49: 0.1 | I49: =IF(COUNT(E49:H49)<4,"UNAVAILABLE",IF(ABS(G49)<=H49,"PASS","FAIL")) -> PASS | J49: Cash dividend equals the retained-earnings charge.
C50: Buyback cash and equity | D50: FY2027E | E50: ='02 Model'!H114 -> -524 | F50: ='03 Schedules'!H244 -> -524 | G50: =E50-F50 -> 0 | H50: 0.1 | I50: =IF(COUNT(E50:H50)<4,"UNAVAILABLE",IF(ABS(G50)<=H50,"PASS","FAIL")) -> PASS | J50: Cash repurchase equals the retained-earnings charge.
C51: Net tax balance roll-forward | D51: FY2027E | E51: =SUM('02 Model'!H50,'02 Model'!H62,'02 Model'!H71) -> -75.882255 | F51: =SUM('02 Model'!G50,'02 Model'!G62,'02 Model'!G71)+'02 Model'!H29-'02 Model'!H98+'03 Schedules'!H248 -> -75.882255 | G51: =E51-F51 -> 0 | H51: 0.1 | I51: =IF(COUNT(E51:H51)<4,"UNAVAILABLE",IF(ABS(G51)<=H51,"PASS","FAIL")) -> PASS | J51: Tax expense, cash payment and direct equity tax credit.
C52: Closing cash definition bridge | D52: FY2028E | E52: ='02 Model'!I51-'02 Model'!I137 -> 36 | F52: ='02 Model'!H51-'02 Model'!H137 -> 36 | G52: =E52-F52 -> 0 | H52: 0.1 | I52: =IF(COUNT(E52:H52)<4,"UNAVAILABLE",IF(ABS(G52)<=H52,"PASS","FAIL")) -> PASS | J52: Prior-period cash classification difference carried forward.
C53: Gross-debt roll-forward | D53: FY2028E | E53: ='03 Schedules'!I159 -> 696 | F53: ='03 Schedules'!I197 -> 696 | G53: =E53-F53 -> 0 | H53: 0.1 | I53: =IF(COUNT(E53:H53)<4,"UNAVAILABLE",IF(ABS(G53)<=H53,"PASS","FAIL")) -> PASS | J53: Opening gross debt + debt cash receipts / payments.
C54: Debt to balance sheet | D54: FY2028E | E54: ='03 Schedules'!I159 -> 696 | F54: =-SUM('02 Model'!I57:'02 Model'!I58)-'02 Model'!I66 -> 696 | G54: =E54-F54 -> 0 | H54: 0.1 | I54: =IF(COUNT(E54:H54)<4,"UNAVAILABLE",IF(ABS(G54)<=H54,"PASS","FAIL")) -> PASS | J54: Bank debt plus current and non-current bonds.
C55: Finance cost to schedule | D55: FY2028E | E55: =-'02 Model'!I27 -> 82.179817 | F55: ='03 Schedules'!I171+'03 Schedules'!I172+'03 Schedules'!I173 -> 82.179817 | G55: =E55-F55 -> 0 | H55: 0.1 | I55: =IF(COUNT(E55:H55)<4,"UNAVAILABLE",IF(ABS(G55)<=H55,"PASS","FAIL")) -> PASS | J55: Borrowing, lease and other finance costs.
C56: Cash interest consistency | D56: FY2028E | E56: =-'02 Model'!I123 -> 82.179817 | F56: ='03 Schedules'!I171+'03 Schedules'!I172 -> 82.179817 | G56: =E56-F56 -> 0 | H56: 0.1 | I56: =IF(COUNT(E56:H56)<4,"UNAVAILABLE",IF(ABS(G56)<=H56,"PASS","FAIL")) -> PASS | J56: Interest paid reconciles to borrowing and lease interest.
C57: Finance income | D57: FY2028E | E57: ='02 Model'!I26 -> 5.731815 | F57: ='03 Schedules'!I168+'03 Schedules'!I169 -> 5.731815 | G57: =E57-F57 -> 0 | H57: 0.1 | I57: =IF(COUNT(E57:H57)<4,"UNAVAILABLE",IF(ABS(G57)<=H57,"PASS","FAIL")) -> PASS | J57: Opening cash yield plus other finance income.
C58: Lease liability roll-forward | D58: FY2028E | E58: =-('02 Model'!I60+'02 Model'!I68) -> 940.29382 | F58: ='03 Schedules'!I76+'03 Schedules'!I77+'03 Schedules'!I78+'03 Schedules'!I79+'03 Schedules'!I80+'03 Schedules'!I82+'03 Schedules'!I83+'03 Schedules'!I84 -> 940.29382 | G58: =E58-F58 -> 0 | H58: 0.1 | I58: =IF(COUNT(E58:H58)<4,"UNAVAILABLE",IF(ABS(G58)<=H58,"PASS","FAIL")) -> PASS | J58: Opening, additions, interest, payments, disposals and FX.
C59: Lease liability split | D59: FY2028E | E59: ='03 Schedules'!I85 -> 940.29382 | F59: ='03 Schedules'!I87+'03 Schedules'!I88 -> 940.29382 | G59: =E59-F59 -> 0 | H59: 0.1 | I59: =IF(COUNT(E59:H59)<4,"UNAVAILABLE",IF(ABS(G59)<=H59,"PASS","FAIL")) -> PASS | J59: Current plus non-current classification.
C60: PP&E roll-forward | D60: FY2028E | E60: ='02 Model'!I37 -> 847.7 | F60: =SUM('03 Schedules'!I19:I22) -> 847.7 | G60: =E60-F60 -> 0 | H60: 0.1 | I60: =IF(COUNT(E60:H60)<4,"UNAVAILABLE",IF(ABS(G60)<=H60,"PASS","FAIL")) -> PASS | J60: Closing asset equals opening plus scheduled changes.
C61: Intangibles roll-forward | D61: FY2028E | E61: ='02 Model'!I38 -> 656.7 | F61: =SUM('03 Schedules'!I40:I43) -> 656.7 | G61: =E61-F61 -> 0 | H61: 0.1 | I61: =IF(COUNT(E61:H61)<4,"UNAVAILABLE",IF(ABS(G61)<=H61,"PASS","FAIL")) -> PASS | J61: Closing asset equals opening plus scheduled changes.
C62: ROU assets roll-forward | D62: FY2028E | E62: ='02 Model'!I39 -> 708.1 | F62: =SUM('03 Schedules'!I68:I73) -> 708.1 | G62: =E62-F62 -> 0 | H62: 0.1 | I62: =IF(COUNT(E62:H62)<4,"UNAVAILABLE",IF(ABS(G62)<=H62,"PASS","FAIL")) -> PASS | J62: Closing asset equals opening plus scheduled changes.
C63: Associates roll-forward | D63: FY2028E | E63: ='02 Model'!I40 -> 51.7 | F63: =SUM('03 Schedules'!I46:I49) -> 51.7 | G63: =E63-F63 -> 0 | H63: 0.1 | I63: =IF(COUNT(E63:H63)<4,"UNAVAILABLE",IF(ABS(G63)<=H63,"PASS","FAIL")) -> PASS | J63: Closing asset equals opening plus scheduled changes.
C64: Inventory cash reconciliation | D64: FY2028E | E64: ='03 Schedules'!I357 -> -111.99629 | F64: =-('02 Model'!I46-'02 Model'!H46)-('02 Model'!I48-'02 Model'!H48) -> -111.99629 | G64: =E64-F64 -> 0 | H64: 0.1 | I64: =IF(COUNT(E64:H64)<4,"UNAVAILABLE",IF(ABS(G64)<=H64,"PASS","FAIL")) -> PASS | J64: Inventory and right-of-return asset both included.
C65: Receivables cash reconciliation | D65: FY2028E | E65: ='03 Schedules'!I358 -> -43.81531 | F65: ='02 Model'!H47-'02 Model'!I47 -> -43.81531 | G65: =E65-F65 -> 0 | H65: 0.1 | I65: =IF(COUNT(E65:H65)<4,"UNAVAILABLE",IF(ABS(G65)<=H65,"PASS","FAIL")) -> PASS | J65: Credit book and other receivable components.
C66: Payables cash reconciliation | D66: FY2028E | E66: ='03 Schedules'!I359 -> 43.043685 | F66: ='02 Model'!H59-'02 Model'!I59 -> 43.043685 | G66: =E66-F66 -> 0 | H66: 0.1 | I66: =IF(COUNT(E66:H66)<4,"UNAVAILABLE",IF(ABS(G66)<=H66,"PASS","FAIL")) -> PASS | J66: Positive liability growth is a cash source.
C67: Receivables composition | D67: FY2028E | E67: ='02 Model'!I47 -> 1691.7371 | F67: =SUM('03 Schedules'!I113:I117) -> 1691.7371 | G67: =E67-F67 -> 0 | H67: 0.1 | I67: =IF(COUNT(E67:H67)<4,"UNAVAILABLE",IF(ABS(G67)<=H67,"PASS","FAIL")) -> PASS | J67: Sum of the component receivable accounts.
C68: Payables composition | D68: FY2028E | E68: =-'02 Model'!I59 -> 1269.152 | F68: =SUM('03 Schedules'!I123:I129) -> 1269.152 | G68: =E68-F68 -> 0 | H68: 0.1 | I68: =IF(COUNT(E68:H68)<4,"UNAVAILABLE",IF(ABS(G68)<=H68,"PASS","FAIL")) -> PASS | J68: Sum of the component payable accounts.
C69: Retained earnings roll-forward | D69: FY2028E | E69: ='02 Model'!I86 -> 3821.341 | F69: =SUM('03 Schedules'!I241:I252) -> 3821.341 | G69: =E69-F69 -> 0 | H69: 0.1 | I69: =IF(COUNT(E69:H69)<4,"UNAVAILABLE",IF(ABS(G69)<=H69,"PASS","FAIL")) -> PASS | J69: Owners’ profit, ordinary and special returns, ESOT, equity tax.
C70: Owners and NCI earnings | D70: FY2028E | E70: ='02 Model'!I30 -> 1007.6564 | F70: ='03 Schedules'!I242+('02 Model'!I30*'03 Schedules'!I210) -> 1007.6564 | G70: =E70-F70 -> 0 | H70: 0.1 | I70: =IF(COUNT(E70:H70)<4,"UNAVAILABLE",IF(ABS(G70)<=H70,"PASS","FAIL")) -> PASS | J70: Owners’ share plus NCI share equals total net income.
C71: NCI roll-forward | D71: FY2028E | E71: ='02 Model'!I88 -> 123.12068 | F71: ='02 Model'!H88+'02 Model'!I30-'03 Schedules'!I242+'02 Model'!I130 -> 123.12068 | G71: =E71-F71 -> 1.1368684e-13 | H71: 0.1 | I71: =IF(COUNT(E71:H71)<4,"UNAVAILABLE",IF(ABS(G71)<=H71,"PASS","FAIL")) -> PASS | J71: NCI opening balance, earnings and dividends.
C72: Total capex | D72: FY2028E | E72: =-'02 Model'!I102-'02 Model'!I106 -> 252 | F72: ='01 Assumptions'!I24 -> 252 | G72: =E72-F72 -> 0 | H72: 0.1 | I72: =IF(COUNT(E72:H72)<4,"UNAVAILABLE",IF(ABS(G72)<=H72,"PASS","FAIL")) -> PASS | J72: PP&E and intangible cash capex equal the approved total.
C73: Dividend cash and equity | D73: FY2028E | E73: ='02 Model'!I129 -> -340.4 | F73: ='03 Schedules'!I249 -> -340.4 | G73: =E73-F73 -> 0 | H73: 0.1 | I73: =IF(COUNT(E73:H73)<4,"UNAVAILABLE",IF(ABS(G73)<=H73,"PASS","FAIL")) -> PASS | J73: Cash dividend equals the retained-earnings charge.
C74: Buyback cash and equity | D74: FY2028E | E74: ='02 Model'!I114 -> -461.48248 | F74: ='03 Schedules'!I244 -> -461.48248 | G74: =E74-F74 -> 0 | H74: 0.1 | I74: =IF(COUNT(E74:H74)<4,"UNAVAILABLE",IF(ABS(G74)<=H74,"PASS","FAIL")) -> PASS | J74: Cash repurchase equals the retained-earnings charge.
C75: Net tax balance roll-forward | D75: FY2028E | E75: =SUM('02 Model'!I50,'02 Model'!I62,'02 Model'!I71) -> -75.882255 | F75: =SUM('02 Model'!H50,'02 Model'!H62,'02 Model'!H71)+'02 Model'!I29-'02 Model'!I98+'03 Schedules'!I248 -> -75.882255 | G75: =E75-F75 -> 0 | H75: 0.1 | I75: =IF(COUNT(E75:H75)<4,"UNAVAILABLE",IF(ABS(G75)<=H75,"PASS","FAIL")) -> PASS | J75: Tax expense, cash payment and direct equity tax credit.
C76: Capital allocation | D76: FY2028E | E76: =-'02 Model'!I114-'02 Model'!I128 -> 461.48248 | F76: ='03 Schedules'!I319 -> 461.48248 | G76: =E76-F76 -> 0 | H76: 0.1 | I76: =IF(COUNT(E76:H76)<4,"UNAVAILABLE",IF(ABS(G76)<=H76,"PASS","FAIL")) -> PASS | J76: Residual return allocated once between buyback and capital return.
C77: Debt instruments | D77: FY2028E | E77: ='03 Schedules'!I159 -> 696 | F77: ='03 Schedules'!I187 -> 696 | G77: =E77-F77 -> 0 | H77: 0.1 | I77: =IF(COUNT(E77:H77)<4,"UNAVAILABLE",IF(ABS(G77)<=H77,"PASS","FAIL")) -> PASS | J77: Instrument balances equal total gross debt.
C78: Lease additions match | D78: FY2028E | E78: ='03 Schedules'!I69 -> 125 | F78: ='03 Schedules'!I77 -> 125 | G78: =E78-F78 -> 0 | H78: 0.1 | I78: =IF(COUNT(E78:H78)<4,"UNAVAILABLE",IF(ABS(G78)<=H78,"PASS","FAIL")) -> PASS | J78: ROU and liability additions have matching values.
C79: Closing cash definition bridge | D79: FY2029E | E79: ='02 Model'!J51-'02 Model'!J137 -> 36 | F79: ='02 Model'!I51-'02 Model'!I137 -> 36 | G79: =E79-F79 -> 0 | H79: 0.1 | I79: =IF(COUNT(E79:H79)<4,"UNAVAILABLE",IF(ABS(G79)<=H79,"PASS","FAIL")) -> PASS | J79: Prior-period cash classification difference carried forward.
C80: Gross-debt roll-forward | D80: FY2029E | E80: ='03 Schedules'!J159 -> 696 | F80: ='03 Schedules'!J197 -> 696 | G80: =E80-F80 -> 0 | H80: 0.1 | I80: =IF(COUNT(E80:H80)<4,"UNAVAILABLE",IF(ABS(G80)<=H80,"PASS","FAIL")) -> PASS | J80: Opening gross debt + debt cash receipts / payments.
C81: Debt to balance sheet | D81: FY2029E | E81: ='03 Schedules'!J159 -> 696 | F81: =-SUM('02 Model'!J57:'02 Model'!J58)-'02 Model'!J66 -> 696 | G81: =E81-F81 -> 0 | H81: 0.1 | I81: =IF(COUNT(E81:H81)<4,"UNAVAILABLE",IF(ABS(G81)<=H81,"PASS","FAIL")) -> PASS | J81: Bank debt plus current and non-current bonds.
C82: Finance cost to schedule | D82: FY2029E | E82: =-'02 Model'!J27 -> 80.48586 | F82: ='03 Schedules'!J171+'03 Schedules'!J172+'03 Schedules'!J173 -> 80.48586 | G82: =E82-F82 -> 0 | H82: 0.1 | I82: =IF(COUNT(E82:H82)<4,"UNAVAILABLE",IF(ABS(G82)<=H82,"PASS","FAIL")) -> PASS | J82: Borrowing, lease and other finance costs.
C83: Cash interest consistency | D83: FY2029E | E83: =-'02 Model'!J123 -> 80.48586 | F83: ='03 Schedules'!J171+'03 Schedules'!J172 -> 80.48586 | G83: =E83-F83 -> 0 | H83: 0.1 | I83: =IF(COUNT(E83:H83)<4,"UNAVAILABLE",IF(ABS(G83)<=H83,"PASS","FAIL")) -> PASS | J83: Interest paid reconciles to borrowing and lease interest.
C84: Finance income | D84: FY2029E | E84: ='02 Model'!J26 -> 5.2 | F84: ='03 Schedules'!J168+'03 Schedules'!J169 -> 5.2 | G84: =E84-F84 -> 0 | H84: 0.1 | I84: =IF(COUNT(E84:H84)<4,"UNAVAILABLE",IF(ABS(G84)<=H84,"PASS","FAIL")) -> PASS | J84: Opening cash yield plus other finance income.
C85: Lease liability roll-forward | D85: FY2029E | E85: =-('02 Model'!J60+'02 Model'!J68) -> 905.2488 | F85: ='03 Schedules'!J76+'03 Schedules'!J77+'03 Schedules'!J78+'03 Schedules'!J79+'03 Schedules'!J80+'03 Schedules'!J82+'03 Schedules'!J83+'03 Schedules'!J84 -> 905.2488 | G85: =E85-F85 -> 0 | H85: 0.1 | I85: =IF(COUNT(E85:H85)<4,"UNAVAILABLE",IF(ABS(G85)<=H85,"PASS","FAIL")) -> PASS | J85: Opening, additions, interest, payments, disposals and FX.
C86: Lease liability split | D86: FY2029E | E86: ='03 Schedules'!J85 -> 905.2488 | F86: ='03 Schedules'!J87+'03 Schedules'!J88 -> 905.2488 | G86: =E86-F86 -> 0 | H86: 0.1 | I86: =IF(COUNT(E86:H86)<4,"UNAVAILABLE",IF(ABS(G86)<=H86,"PASS","FAIL")) -> PASS | J86: Current plus non-current classification.
C87: PP&E roll-forward | D87: FY2029E | E87: ='02 Model'!J37 -> 902.7 | F87: =SUM('03 Schedules'!J19:J22) -> 902.7 | G87: =E87-F87 -> 0 | H87: 0.1 | I87: =IF(COUNT(E87:H87)<4,"UNAVAILABLE",IF(ABS(G87)<=H87,"PASS","FAIL")) -> PASS | J87: Closing asset equals opening plus scheduled changes.
C88: Intangibles roll-forward | D88: FY2029E | E88: ='02 Model'!J38 -> 626.7 | F88: =SUM('03 Schedules'!J40:J43) -> 626.7 | G88: =E88-F88 -> 0 | H88: 0.1 | I88: =IF(COUNT(E88:H88)<4,"UNAVAILABLE",IF(ABS(G88)<=H88,"PASS","FAIL")) -> PASS | J88: Closing asset equals opening plus scheduled changes.
C89: ROU assets roll-forward | D89: FY2029E | E89: ='02 Model'!J39 -> 700.1 | F89: =SUM('03 Schedules'!J68:J73) -> 700.1 | G89: =E89-F89 -> 0 | H89: 0.1 | I89: =IF(COUNT(E89:H89)<4,"UNAVAILABLE",IF(ABS(G89)<=H89,"PASS","FAIL")) -> PASS | J89: Closing asset equals opening plus scheduled changes.
C90: Associates roll-forward | D90: FY2029E | E90: ='02 Model'!J40 -> 60.7 | F90: =SUM('03 Schedules'!J46:J49) -> 60.7 | G90: =E90-F90 -> 0 | H90: 0.1 | I90: =IF(COUNT(E90:H90)<4,"UNAVAILABLE",IF(ABS(G90)<=H90,"PASS","FAIL")) -> PASS | J90: Closing asset equals opening plus scheduled changes.
C91: Inventory cash reconciliation | D91: FY2029E | E91: ='03 Schedules'!J357 -> -7.2135324 | F91: =-('02 Model'!J46-'02 Model'!I46)-('02 Model'!J48-'02 Model'!I48) -> -7.2135324 | G91: =E91-F91 -> 0 | H91: 0.1 | I91: =IF(COUNT(E91:H91)<4,"UNAVAILABLE",IF(ABS(G91)<=H91,"PASS","FAIL")) -> PASS | J91: Inventory and right-of-return asset both included.
C92: Receivables cash reconciliation | D92: FY2029E | E92: ='03 Schedules'!J358 -> -45.219843 | F92: ='02 Model'!I47-'02 Model'!J47 -> -45.219843 | G92: =E92-F92 -> 0 | H92: 0.1 | I92: =IF(COUNT(E92:H92)<4,"UNAVAILABLE",IF(ABS(G92)<=H92,"PASS","FAIL")) -> PASS | J92: Credit book and other receivable components.
C93: Payables cash reconciliation | D93: FY2029E | E93: ='03 Schedules'!J359 -> 95.397987 | F93: ='02 Model'!I59-'02 Model'!J59 -> 95.397987 | G93: =E93-F93 -> 0 | H93: 0.1 | I93: =IF(COUNT(E93:H93)<4,"UNAVAILABLE",IF(ABS(G93)<=H93,"PASS","FAIL")) -> PASS | J93: Positive liability growth is a cash source.
C94: Receivables composition | D94: FY2029E | E94: ='02 Model'!J47 -> 1736.957 | F94: =SUM('03 Schedules'!J113:J117) -> 1736.957 | G94: =E94-F94 -> 0 | H94: 0.1 | I94: =IF(COUNT(E94:H94)<4,"UNAVAILABLE",IF(ABS(G94)<=H94,"PASS","FAIL")) -> PASS | J94: Sum of the component receivable accounts.
C95: Payables composition | D95: FY2029E | E95: =-'02 Model'!J59 -> 1364.55 | F95: =SUM('03 Schedules'!J123:J129) -> 1364.55 | G95: =E95-F95 -> 0 | H95: 0.1 | I95: =IF(COUNT(E95:H95)<4,"UNAVAILABLE",IF(ABS(G95)<=H95,"PASS","FAIL")) -> PASS | J95: Sum of the component payable accounts.
C96: Retained earnings roll-forward | D96: FY2029E | E96: ='02 Model'!J86 -> 3865.8895 | F96: =SUM('03 Schedules'!J241:J252) -> 3865.8895 | G96: =E96-F96 -> 0 | H96: 0.1 | I96: =IF(COUNT(E96:H96)<4,"UNAVAILABLE",IF(ABS(G96)<=H96,"PASS","FAIL")) -> PASS | J96: Owners’ profit, ordinary and special returns, ESOT, equity tax.
C97: Owners and NCI earnings | D97: FY2029E | E97: ='02 Model'!J30 -> 1070.2901 | F97: ='03 Schedules'!J242+('02 Model'!J30*'03 Schedules'!J210) -> 1070.2901 | G97: =E97-F97 -> 0 | H97: 0.1 | I97: =IF(COUNT(E97:H97)<4,"UNAVAILABLE",IF(ABS(G97)<=H97,"PASS","FAIL")) -> PASS | J97: Owners’ share plus NCI share equals total net income.
C98: NCI roll-forward | D98: FY2029E | E98: ='02 Model'!J88 -> 126.65264 | F98: ='02 Model'!I88+'02 Model'!J30-'03 Schedules'!J242+'02 Model'!J130 -> 126.65264 | G98: =E98-F98 -> 0 | H98: 0.1 | I98: =IF(COUNT(E98:H98)<4,"UNAVAILABLE",IF(ABS(G98)<=H98,"PASS","FAIL")) -> PASS | J98: NCI opening balance, earnings and dividends.
C99: Total capex | D99: FY2029E | E99: =-'02 Model'!J102-'02 Model'!J106 -> 227 | F99: ='01 Assumptions'!J24 -> 227 | G99: =E99-F99 -> 0 | H99: 0.1 | I99: =IF(COUNT(E99:H99)<4,"UNAVAILABLE",IF(ABS(G99)<=H99,"PASS","FAIL")) -> PASS | J99: PP&E and intangible cash capex equal the approved total.
C100: Dividend cash and equity | D100: FY2029E | E100: ='02 Model'!J129 -> -374.1 | F100: ='03 Schedules'!J249 -> -374.1 | G100: =E100-F100 -> 0 | H100: 0.1 | I100: =IF(COUNT(E100:H100)<4,"UNAVAILABLE",IF(ABS(G100)<=H100,"PASS","FAIL")) -> PASS | J100: Cash dividend equals the retained-earnings charge.
C101: Buyback cash and equity | D101: FY2029E | E101: ='02 Model'!J114 -> -665.86848 | F101: ='03 Schedules'!J244 -> -665.86848 | G101: =E101-F101 -> 0 | H101: 0.1 | I101: =IF(COUNT(E101:H101)<4,"UNAVAILABLE",IF(ABS(G101)<=H101,"PASS","FAIL")) -> PASS | J101: Cash repurchase equals the retained-earnings charge.
C102: Net tax balance roll-forward | D102: FY2029E | E102: =SUM('02 Model'!J50,'02 Model'!J62,'02 Model'!J71) -> -75.882255 | F102: =SUM('02 Model'!I50,'02 Model'!I62,'02 Model'!I71)+'02 Model'!J29-'02 Model'!J98+'03 Schedules'!J248 -> -75.882255 | G102: =E102-F102 -> 0 | H102: 0.1 | I102: =IF(COUNT(E102:H102)<4,"UNAVAILABLE",IF(ABS(G102)<=H102,"PASS","FAIL")) -> PASS | J102: Tax expense, cash payment and direct equity tax credit.
C103: Capital allocation | D103: FY2029E | E103: =-'02 Model'!J114-'02 Model'!J128 -> 665.86848 | F103: ='03 Schedules'!J319 -> 665.86848 | G103: =E103-F103 -> 0 | H103: 0.1 | I103: =IF(COUNT(E103:H103)<4,"UNAVAILABLE",IF(ABS(G103)<=H103,"PASS","FAIL")) -> PASS | J103: Residual return allocated once between buyback and capital return.
C104: Debt instruments | D104: FY2029E | E104: ='03 Schedules'!J159 -> 696 | F104: ='03 Schedules'!J187 -> 696 | G104: =E104-F104 -> 0 | H104: 0.1 | I104: =IF(COUNT(E104:H104)<4,"UNAVAILABLE",IF(ABS(G104)<=H104,"PASS","FAIL")) -> PASS | J104: Instrument balances equal total gross debt.
C105: Lease additions match | D105: FY2029E | E105: ='03 Schedules'!J69 -> 130 | F105: ='03 Schedules'!J77 -> 130 | G105: =E105-F105 -> 0 | H105: 0.1 | I105: =IF(COUNT(E105:H105)<4,"UNAVAILABLE",IF(ABS(G105)<=H105,"PASS","FAIL")) -> PASS | J105: ROU and liability additions have matching values.
...

Sheet 05 DCF Valuation
C2: NEXT plc — base-case DCF valuation
C3: FCFF, leases treated as operating costs. £m except £ per share and shares in millions. Base Case.
C4: Return to Cover
C5: Final build: 10 September 2026. Valuation date: 7 September 2026. Market-input corroboration reviewed through 10 September; operating forecasts retain their 5 August cutoff. January balance-sheet proxies remain.
C7: Base-case DCF valuation
C8: Implied value per diluted share | G8: =G203 -> 100.96145 | H8: Intrinsic value conditional on the assumptions, not a guaranteed price.
C9: Observed market price | G9: =G52 -> 155 | H9: LSEG via Investors Chronicle, 7 Sep 2026, 16:35 BST.
C10: Implied upside / (downside) | G10: =G8/G9-1 -> -0.34863583 | H10: No input has been chosen to force agreement with the market.
C11: Enterprise value | G11: =G178 -> 12677.742 | H11: Operating value after lease cash costs.
C12: Equity value | G12: =G200 -> 11757.167
C13: Calculated WACC | G13: =G73 -> 0.098821446 | H13: CAPM and gross financial-debt weights; lease debt excluded.
C14: Terminal growth | G14: =G156 -> 0.02 | H14: Independent perpetual nominal GBP growth assumption.
C15: PV terminal value / enterprise value | G15: =G173 -> 0.51513942 | H15: A high percentage makes terminal assumptions particularly important.
C16: Calculation-check failures | G16: =COUNTIFS(G218:G241,"FAIL")+COUNTIFS(G248:G257,"FAIL") -> 0 | H16: Zero indicates that the listed calculation checks pass; valuation proxies remain judgement-sensitive.
C17: Mature incremental ROIC | G17: =G155 -> 0.2
C18: Review limitations: stale capital-structure / ESOT balances, proxy dilution and NCI values, annual FY2027 cash-flow proration, beta methodology and terminal reinvestment. See the learning guide.
C20: WACC × terminal growth — implied £ per share
C22: Formula-driven sensitivity. Columns vary terminal growth; rows vary WACC. Five-year fade held fixed; terminal reinvestment recalculates. Outlined centre is the base case.
G25: =G203 -> 100.96145 | H25: =$G$156+-2*$G$76 -> 0.01 | I25: =$G$156+-1*$G$76 -> 0.015 | J25: =$G$156+0*$G$76 -> 0.02 | K25: =$G$156+1*$G$76 -> 0.025 | L25: =$G$156+2*$G$76 -> 0.03
G26: =$G$73+-4*$G$75 -> 0.078821446 | H26: =(SUM($H$109/(1+$G26)^$H$87,$I$109/(1+$G26)^$I$87,$J$109/(1+$G26)^$J$87,$K$109/(1+$G26)^$K$87,$L$109/(1+$G26)^$L$87)+SUM($H$134*(1-$H$129/$G$155)/(1+$G26)^$H$139,$I$134*(1-$I$129/$G$155)/(1+$G26)^$I$139,$J$134*(1-$J$129/$G$155)/(1+$G26)^$J$139,$K$134*(1-$K$129/$G$155)/(1+$G26)^$K$139,$L$134*(1-$L$129/$G$155)/(1+$G26)^$L$139)+($L$130*(1+H$25)*$G$153*(1-$G$154)*(1-H$25/$G$155)/($G26-H$25)/(1+$G26)^$L$139)+$G$199)/$G$201 -> 129.48085 | I26: =(SUM($H$109/(1+$G26)^$H$87,$I$109/(1+$G26)^$I$87,$J$109/(1+$G26)^$J$87,$K$109/(1+$G26)^$K$87,$L$109/(1+$G26)^$L$87)+SUM($H$134*(1-$H$129/$G$155)/(1+$G26)^$H$139,$I$134*(1-$I$129/$G$155)/(1+$G26)^$I$139,$J$134*(1-$J$129/$G$155)/(1+$G26)^$J$139,$K$134*(1-$K$129/$G$155)/(1+$G26)^$K$139,$L$134*(1-$L$129/$G$155)/(1+$G26)^$L$139)+($L$130*(1+I$25)*$G$153*(1-$G$154)*(1-I$25/$G$155)/($G26-I$25)/(1+$G26)^$L$139)+$G$199)/$G$201 -> 133.8811 | J26: =(SUM($H$109/(1+$G26)^$H$87,$I$109/(1+$G26)^$I$87,$J$109/(1+$G26)^$J$87,$K$109/(1+$G26)^$K$87,$L$109/(1+$G26)^$L$87)+SUM($H$134*(1-$H$129/$G$155)/(1+$G26)^$H$139,$I$134*(1-$I$129/$G$155)/(1+$G26)^$I$139,$J$134*(1-$J$129/$G$155)/(1+$G26)^$J$139,$K$134*(1-$K$129/$G$155)/(1+$G26)^$K$139,$L$134*(1-$L$129/$G$155)/(1+$G26)^$L$139)+($L$130*(1+J$25)*$G$153*(1-$G$154)*(1-J$25/$G$155)/($G26-J$25)/(1+$G26)^$L$139)+$G$199)/$G$201 -> 139.00511 | K26: =(SUM($H$109/(1+$G26)^$H$87,$I$109/(1+$G26)^$I$87,$J$109/(1+$G26)^$J$87,$K$109/(1+$G26)^$K$87,$L$109/(1+$G26)^$L$87)+SUM($H$134*(1-$H$129/$G$155)/(1+$G26)^$H$139,$I$134*(1-$I$129/$G$155)/(1+$G26)^$I$139,$J$134*(1-$J$129/$G$155)/(1+$G26)^$J$139,$K$134*(1-$K$129/$G$155)/(1+$G26)^$K$139,$L$134*(1-$L$129/$G$155)/(1+$G26)^$L$139)+($L$130*(1+K$25)*$G$153*(1-$G$154)*(1-K$25/$G$155)/($G26-K$25)/(1+$G26)^$L$139)+$G$199)/$G$201 -> 145.05458 | L26: =(SUM($H$109/(1+$G26)^$H$87,$I$109/(1+$G26)^$I$87,$J$109/(1+$G26)^$J$87,$K$109/(1+$G26)^$K$87,$L$109/(1+$G26)^$L$87)+SUM($H$134*(1-$H$129/$G$155)/(1+$G26)^$H$139,$I$134*(1-$I$129/$G$155)/(1+$G26)^$I$139,$J$134*(1-$J$129/$G$155)/(1+$G26)^$J$139,$K$134*(1-$K$129/$G$155)/(1+$G26)^$K$139,$L$134*(1-$L$129/$G$155)/(1+$G26)^$L$139)+($L$130*(1+L$25)*$G$153*(1-$G$154)*(1-L$25/$G$155)/($G26-L$25)/(1+$G26)^$L$139)+$G$199)/$G$201 -> 152.31385
G27: =$G$73+-3*$G$75 -> 0.083821446 | H27: =(SUM($H$109/(1+$G27)^$H$87,$I$109/(1+$G27)^$I$87,$J$109/(1+$G27)^$J$87,$K$109/(1+$G27)^$K$87,$L$109/(1+$G27)^$L$87)+SUM($H$134*(1-$H$129/$G$155)/(1+$G27)^$H$139,$I$134*(1-$I$129/$G$155)/(1+$G27)^$I$139,$J$134*(1-$J$129/$G$155)/(1+$G27)^$J$139,$K$134*(1-$K$129/$G$155)/(1+$G27)^$K$139,$L$134*(1-$L$129/$G$155)/(1+$G27)^$L$139)+($L$130*(1+H$25)*$G$153*(1-$G$154)*(1-H$25/$G$155)/($G27-H$25)/(1+$G27)^$L$139)+$G$199)/$G$201 -> 119.64946 | I27: =(SUM($H$109/(1+$G27)^$H$87,$I$109/(1+$G27)^$I$87,$J$109/(1+$G27)^$J$87,$K$109/(1+$G27)^$K$87,$L$109/(1+$G27)^$L$87)+SUM($H$134*(1-$H$129/$G$155)/(1+$G27)^$H$139,$I$134*(1-$I$129/$G$155)/(1+$G27)^$I$139,$J$134*(1-$J$129/$G$155)/(1+$G27)^$J$139,$K$134*(1-$K$129/$G$155)/(1+$G27)^$K$139,$L$134*(1-$L$129/$G$155)/(1+$G27)^$L$139)+($L$130*(1+I$25)*$G$153*(1-$G$154)*(1-I$25/$G$155)/($G27-I$25)/(1+$G27)^$L$139)+$G$199)/$G$201 -> 123.18087 | J27: =(SUM($H$109/(1+$G27)^$H$87,$I$109/(1+$G27)^$I$87,$J$109/(1+$G27)^$J$87,$K$109/(1+$G27)^$K$87,$L$109/(1+$G27)^$L$87)+SUM($H$134*(1-$H$129/$G$155)/(1+$G27)^$H$139,$I$134*(1-$I$129/$G$155)/(1+$G27)^$I$139,$J$134*(1-$J$129/$G$155)/(1+$G27)^$J$139,$K$134*(1-$K$129/$G$155)/(1+$G27)^$K$139,$L$134*(1-$L$129/$G$155)/(1+$G27)^$L$139)+($L$130*(1+J$25)*$G$153*(1-$G$154)*(1-J$25/$G$155)/($G27-J$25)/(1+$G27)^$L$139)+$G$199)/$G$201 -> 127.24414 | K27: =(SUM($H$109/(1+$G27)^$H$87,$I$109/(1+$G27)^$I$87,$J$109/(1+$G27)^$J$87,$K$109/(1+$G27)^$K$87,$L$109/(1+$G27)^$L$87)+SUM($H$134*(1-$H$129/$G$155)/(1+$G27)^$H$139,$I$134*(1-$I$129/$G$155)/(1+$G27)^$I$139,$J$134*(1-$J$129/$G$155)/(1+$G27)^$J$139,$K$134*(1-$K$129/$G$155)/(1+$G27)^$K$139,$L$134*(1-$L$129/$G$155)/(1+$G27)^$L$139)+($L$130*(1+K$25)*$G$153*(1-$G$154)*(1-K$25/$G$155)/($G27-K$25)/(1+$G27)^$L$139)+$G$199)/$G$201 -> 131.97491 | L27: =(SUM($H$109/(1+$G27)^$H$87,$I$109/(1+$G27)^$I$87,$J$109/(1+$G27)^$J$87,$K$109/(1+$G27)^$K$87,$L$109/(1+$G27)^$L$87)+SUM($H$134*(1-$H$129/$G$155)/(1+$G27)^$H$139,$I$134*(1-$I$129/$G$155)/(1+$G27)^$I$139,$J$134*(1-$J$129/$G$155)/(1+$G27)^$J$139,$K$134*(1-$K$129/$G$155)/(1+$G27)^$K$139,$L$134*(1-$L$129/$G$155)/(1+$G27)^$L$139)+($L$130*(1+L$25)*$G$153*(1-$G$154)*(1-L$25/$G$155)/($G27-L$25)/(1+$G27)^$L$139)+$G$199)/$G$201 -> 137.55921
G28: =$G$73+-2*$G$75 -> 0.088821446 | H28: =(SUM($H$109/(1+$G28)^$H$87,$I$109/(1+$G28)^$I$87,$J$109/(1+$G28)^$J$87,$K$109/(1+$G28)^$K$87,$L$109/(1+$G28)^$L$87)+SUM($H$134*(1-$H$129/$G$155)/(1+$G28)^$H$139,$I$134*(1-$I$129/$G$155)/(1+$G28)^$I$139,$J$134*(1-$J$129/$G$155)/(1+$G28)^$J$139,$K$134*(1-$K$129/$G$155)/(1+$G28)^$K$139,$L$134*(1-$L$129/$G$155)/(1+$G28)^$L$139)+($L$130*(1+H$25)*$G$153*(1-$G$154)*(1-H$25/$G$155)/($G28-H$25)/(1+$G28)^$L$139)+$G$199)/$G$201 -> 111.08487 | I28: =(SUM($H$109/(1+$G28)^$H$87,$I$109/(1+$G28)^$I$87,$J$109/(1+$G28)^$J$87,$K$109/(1+$G28)^$K$87,$L$109/(1+$G28)^$L$87)+SUM($H$134*(1-$H$129/$G$155)/(1+$G28)^$H$139,$I$134*(1-$I$129/$G$155)/(1+$G28)^$I$139,$J$134*(1-$J$129/$G$155)/(1+$G28)^$J$139,$K$134*(1-$K$129/$G$155)/(1+$G28)^$K$139,$L$134*(1-$L$129/$G$155)/(1+$G28)^$L$139)+($L$130*(1+I$25)*$G$153*(1-$G$154)*(1-I$25/$G$155)/($G28-I$25)/(1+$G28)^$L$139)+$G$199)/$G$201 -> 113.94489 | J28: =(SUM($H$109/(1+$G28)^$H$87,$I$109/(1+$G28)^$I$87,$J$109/(1+$G28)^$J$87,$K$109/(1+$G28)^$K$87,$L$109/(1+$G28)^$L$87)+SUM($H$134*(1-$H$129/$G$155)/(1+$G28)^$H$139,$I$134*(1-$I$129/$G$155)/(1+$G28)^$I$139,$J$134*(1-$J$129/$G$155)/(1+$G28)^$J$139,$K$134*(1-$K$129/$G$155)/(1+$G28)^$K$139,$L$134*(1-$L$129/$G$155)/(1+$G28)^$L$139)+($L$130*(1+J$25)*$G$153*(1-$G$154)*(1-J$25/$G$155)/($G28-J$25)/(1+$G28)^$L$139)+$G$199)/$G$201 -> 117.20143 | K28: =(SUM($H$109/(1+$G28)^$H$87,$I$109/(1+$G28)^$I$87,$J$109/(1+$G28)^$J$87,$K$109/(1+$G28)^$K$87,$L$109/(1+$G28)^$L$87)+SUM($H$134*(1-$H$129/$G$155)/(1+$G28)^$H$139,$I$134*(1-$I$129/$G$155)/(1+$G28)^$I$139,$J$134*(1-$J$129/$G$155)/(1+$G28)^$J$139,$K$134*(1-$K$129/$G$155)/(1+$G28)^$K$139,$L$134*(1-$L$129/$G$155)/(1+$G28)^$L$139)+($L$130*(1+K$25)*$G$153*(1-$G$154)*(1-K$25/$G$155)/($G28-K$25)/(1+$G28)^$L$139)+$G$199)/$G$201 -> 120.94766 | L28: =(SUM($H$109/(1+$G28)^$H$87,$I$109/(1+$G28)^$I$87,$J$109/(1+$G28)^$J$87,$K$109/(1+$G28)^$K$87,$L$109/(1+$G28)^$L$87)+SUM($H$134*(1-$H$129/$G$155)/(1+$G28)^$H$139,$I$134*(1-$I$129/$G$155)/(1+$G28)^$I$139,$J$134*(1-$J$129/$G$155)/(1+$G28)^$J$139,$K$134*(1-$K$129/$G$155)/(1+$G28)^$K$139,$L$134*(1-$L$129/$G$155)/(1+$G28)^$L$139)+($L$130*(1+L$25)*$G$153*(1-$G$154)*(1-L$25/$G$155)/($G28-L$25)/(1+$G28)^$L$139)+$G$199)/$G$201 -> 125.30848
G29: =$G$73+-1*$G$75 -> 0.093821446 | H29: =(SUM($H$109/(1+$G29)^$H$87,$I$109/(1+$G29)^$I$87,$J$109/(1+$G29)^$J$87,$K$109/(1+$G29)^$K$87,$L$109/(1+$G29)^$L$87)+SUM($H$134*(1-$H$129/$G$155)/(1+$G29)^$H$139,$I$134*(1-$I$129/$G$155)/(1+$G29)^$I$139,$J$134*(1-$J$129/$G$155)/(1+$G29)^$J$139,$K$134*(1-$K$129/$G$155)/(1+$G29)^$K$139,$L$134*(1-$L$129/$G$155)/(1+$G29)^$L$139)+($L$130*(1+H$25)*$G$153*(1-$G$154)*(1-H$25/$G$155)/($G29-H$25)/(1+$G29)^$L$139)+$G$199)/$G$201 -> 103.55958 | I29: =(SUM($H$109/(1+$G29)^$H$87,$I$109/(1+$G29)^$I$87,$J$109/(1+$G29)^$J$87,$K$109/(1+$G29)^$K$87,$L$109/(1+$G29)^$L$87)+SUM($H$134*(1-$H$129/$G$155)/(1+$G29)^$H$139,$I$134*(1-$I$129/$G$155)/(1+$G29)^$I$139,$J$134*(1-$J$129/$G$155)/(1+$G29)^$J$139,$K$134*(1-$K$129/$G$155)/(1+$G29)^$K$139,$L$134*(1-$L$129/$G$155)/(1+$G29)^$L$139)+($L$130*(1+I$25)*$G$153*(1-$G$154)*(1-I$25/$G$155)/($G29-I$25)/(1+$G29)^$L$139)+$G$199)/$G$201 -> 105.89392 | J29: =(SUM($H$109/(1+$G29)^$H$87,$I$109/(1+$G29)^$I$87,$J$109/(1+$G29)^$J$87,$K$109/(1+$G29)^$K$87,$L$109/(1+$G29)^$L$87)+SUM($H$134*(1-$H$129/$G$155)/(1+$G29)^$H$139,$I$134*(1-$I$129/$G$155)/(1+$G29)^$I$139,$J$134*(1-$J$129/$G$155)/(1+$G29)^$J$139,$K$134*(1-$K$129/$G$155)/(1+$G29)^$K$139,$L$134*(1-$L$129/$G$155)/(1+$G29)^$L$139)+($L$130*(1+J$25)*$G$153*(1-$G$154)*(1-J$25/$G$155)/($G29-J$25)/(1+$G29)^$L$139)+$G$199)/$G$201 -> 108.52746 | K29: =(SUM($H$109/(1+$G29)^$H$87,$I$109/(1+$G29)^$I$87,$J$109/(1+$G29)^$J$87,$K$109/(1+$G29)^$K$87,$L$109/(1+$G29)^$L$87)+SUM($H$134*(1-$H$129/$G$155)/(1+$G29)^$H$139,$I$134*(1-$I$129/$G$155)/(1+$G29)^$I$139,$J$134*(1-$J$129/$G$155)/(1+$G29)^$J$139,$K$134*(1-$K$129/$G$155)/(1+$G29)^$K$139,$L$134*(1-$L$129/$G$155)/(1+$G29)^$L$139)+($L$130*(1+K$25)*$G$153*(1-$G$154)*(1-K$25/$G$155)/($G29-K$25)/(1+$G29)^$L$139)+$G$199)/$G$201 -> 111.52541 | L29: =(SUM($H$109/(1+$G29)^$H$87,$I$109/(1+$G29)^$I$87,$J$109/(1+$G29)^$J$87,$K$109/(1+$G29)^$K$87,$L$109/(1+$G29)^$L$87)+SUM($H$134*(1-$H$129/$G$155)/(1+$G29)^$H$139,$I$134*(1-$I$129/$G$155)/(1+$G29)^$I$139,$J$134*(1-$J$129/$G$155)/(1+$G29)^$J$139,$K$134*(1-$K$129/$G$155)/(1+$G29)^$K$139,$L$134*(1-$L$129/$G$155)/(1+$G29)^$L$139)+($L$130*(1+L$25)*$G$153*(1-$G$154)*(1-L$25/$G$155)/($G29-L$25)/(1+$G29)^$L$139)+$G$199)/$G$201 -> 114.97341
G30: =$G$73+0*$G$75 -> 0.098821446 | H30: =(SUM($H$109/(1+$G30)^$H$87,$I$109/(1+$G30)^$I$87,$J$109/(1+$G30)^$J$87,$K$109/(1+$G30)^$K$87,$L$109/(1+$G30)^$L$87)+SUM($H$134*(1-$H$129/$G$155)/(1+$G30)^$H$139,$I$134*(1-$I$129/$G$155)/(1+$G30)^$I$139,$J$134*(1-$J$129/$G$155)/(1+$G30)^$J$139,$K$134*(1-$K$129/$G$155)/(1+$G30)^$K$139,$L$134*(1-$L$129/$G$155)/(1+$G30)^$L$139)+($L$130*(1+H$25)*$G$153*(1-$G$154)*(1-H$25/$G$155)/($G30-H$25)/(1+$G30)^$L$139)+$G$199)/$G$201 -> 96.897327 | I30: =(SUM($H$109/(1+$G30)^$H$87,$I$109/(1+$G30)^$I$87,$J$109/(1+$G30)^$J$87,$K$109/(1+$G30)^$K$87,$L$109/(1+$G30)^$L$87)+SUM($H$134*(1-$H$129/$G$155)/(1+$G30)^$H$139,$I$134*(1-$I$129/$G$155)/(1+$G30)^$I$139,$J$134*(1-$J$129/$G$155)/(1+$G30)^$J$139,$K$134*(1-$K$129/$G$155)/(1+$G30)^$K$139,$L$134*(1-$L$129/$G$155)/(1+$G30)^$L$139)+($L$130*(1+I$25)*$G$153*(1-$G$154)*(1-I$25/$G$155)/($G30-I$25)/(1+$G30)^$L$139)+$G$199)/$G$201 -> 98.815353 | J30: =(SUM($H$109/(1+$G30)^$H$87,$I$109/(1+$G30)^$I$87,$J$109/(1+$G30)^$J$87,$K$109/(1+$G30)^$K$87,$L$109/(1+$G30)^$L$87)+SUM($H$134*(1-$H$129/$G$155)/(1+$G30)^$H$139,$I$134*(1-$I$129/$G$155)/(1+$G30)^$I$139,$J$134*(1-$J$129/$G$155)/(1+$G30)^$J$139,$K$134*(1-$K$129/$G$155)/(1+$G30)^$K$139,$L$134*(1-$L$129/$G$155)/(1+$G30)^$L$139)+($L$130*(1+J$25)*$G$153*(1-$G$154)*(1-J$25/$G$155)/($G30-J$25)/(1+$G30)^$L$139)+$G$199)/$G$201 -> 100.96145 | K30: =(SUM($H$109/(1+$G30)^$H$87,$I$109/(1+$G30)^$I$87,$J$109/(1+$G30)^$J$87,$K$109/(1+$G30)^$K$87,$L$109/(1+$G30)^$L$87)+SUM($H$134*(1-$H$129/$G$155)/(1+$G30)^$H$139,$I$134*(1-$I$129/$G$155)/(1+$G30)^$I$139,$J$134*(1-$J$129/$G$155)/(1+$G30)^$J$139,$K$134*(1-$K$129/$G$155)/(1+$G30)^$K$139,$L$134*(1-$L$129/$G$155)/(1+$G30)^$L$139)+($L$130*(1+K$25)*$G$153*(1-$G$154)*(1-K$25/$G$155)/($G30-K$25)/(1+$G30)^$L$139)+$G$199)/$G$201 -> 103.38194 | L30: =(SUM($H$109/(1+$G30)^$H$87,$I$109/(1+$G30)^$I$87,$J$109/(1+$G30)^$J$87,$K$109/(1+$G30)^$K$87,$L$109/(1+$G30)^$L$87)+SUM($H$134*(1-$H$129/$G$155)/(1+$G30)^$H$139,$I$134*(1-$I$129/$G$155)/(1+$G30)^$I$139,$J$134*(1-$J$129/$G$155)/(1+$G30)^$J$139,$K$134*(1-$K$129/$G$155)/(1+$G30)^$K$139,$L$134*(1-$L$129/$G$155)/(1+$G30)^$L$139)+($L$130*(1+L$25)*$G$153*(1-$G$154)*(1-L$25/$G$155)/($G30-L$25)/(1+$G30)^$L$139)+$G$199)/$G$201 -> 106.13666
G31: =$G$73+1*$G$75 -> 0.10382145 | H31: =(SUM($H$109/(1+$G31)^$H$87,$I$109/(1+$G31)^$I$87,$J$109/(1+$G31)^$J$87,$K$109/(1+$G31)^$K$87,$L$109/(1+$G31)^$L$87)+SUM($H$134*(1-$H$129/$G$155)/(1+$G31)^$H$139,$I$134*(1-$I$129/$G$155)/(1+$G31)^$I$139,$J$134*(1-$J$129/$G$155)/(1+$G31)^$J$139,$K$134*(1-$K$129/$G$155)/(1+$G31)^$K$139,$L$134*(1-$L$129/$G$155)/(1+$G31)^$L$139)+($L$130*(1+H$25)*$G$153*(1-$G$154)*(1-H$25/$G$155)/($G31-H$25)/(1+$G31)^$L$139)+$G$199)/$G$201 -> 90.959483 | I31: =(SUM($H$109/(1+$G31)^$H$87,$I$109/(1+$G31)^$I$87,$J$109/(1+$G31)^$J$87,$K$109/(1+$G31)^$K$87,$L$109/(1+$G31)^$L$87)+SUM($H$134*(1-$H$129/$G$155)/(1+$G31)^$H$139,$I$134*(1-$I$129/$G$155)/(1+$G31)^$I$139,$J$134*(1-$J$129/$G$155)/(1+$G31)^$J$139,$K$134*(1-$K$129/$G$155)/(1+$G31)^$K$139,$L$134*(1-$L$129/$G$155)/(1+$G31)^$L$139)+($L$130*(1+I$25)*$G$153*(1-$G$154)*(1-I$25/$G$155)/($G31-I$25)/(1+$G31)^$L$139)+$G$199)/$G$201 -> 92.544484 | J31: =(SUM($H$109/(1+$G31)^$H$87,$I$109/(1+$G31)^$I$87,$J$109/(1+$G31)^$J$87,$K$109/(1+$G31)^$K$87,$L$109/(1+$G31)^$L$87)+SUM($H$134*(1-$H$129/$G$155)/(1+$G31)^$H$139,$I$134*(1-$I$129/$G$155)/(1+$G31)^$I$139,$J$134*(1-$J$129/$G$155)/(1+$G31)^$J$139,$K$134*(1-$K$129/$G$155)/(1+$G31)^$K$139,$L$134*(1-$L$129/$G$155)/(1+$G31)^$L$139)+($L$130*(1+J$25)*$G$153*(1-$G$154)*(1-J$25/$G$155)/($G31-J$25)/(1+$G31)^$L$139)+$G$199)/$G$201 -> 94.304816 | K31: =(SUM($H$109/(1+$G31)^$H$87,$I$109/(1+$G31)^$I$87,$J$109/(1+$G31)^$J$87,$K$109/(1+$G31)^$K$87,$L$109/(1+$G31)^$L$87)+SUM($H$134*(1-$H$129/$G$155)/(1+$G31)^$H$139,$I$134*(1-$I$129/$G$155)/(1+$G31)^$I$139,$J$134*(1-$J$129/$G$155)/(1+$G31)^$J$139,$K$134*(1-$K$129/$G$155)/(1+$G31)^$K$139,$L$134*(1-$L$129/$G$155)/(1+$G31)^$L$139)+($L$130*(1+K$25)*$G$153*(1-$G$154)*(1-K$25/$G$155)/($G31-K$25)/(1+$G31)^$L$139)+$G$199)/$G$201 -> 96.273843 | L31: =(SUM($H$109/(1+$G31)^$H$87,$I$109/(1+$G31)^$I$87,$J$109/(1+$G31)^$J$87,$K$109/(1+$G31)^$K$87,$L$109/(1+$G31)^$L$87)+SUM($H$134*(1-$H$129/$G$155)/(1+$G31)^$H$139,$I$134*(1-$I$129/$G$155)/(1+$G31)^$I$139,$J$134*(1-$J$129/$G$155)/(1+$G31)^$J$139,$K$134*(1-$K$129/$G$155)/(1+$G31)^$K$139,$L$134*(1-$L$129/$G$155)/(1+$G31)^$L$139)+($L$130*(1+L$25)*$G$153*(1-$G$154)*(1-L$25/$G$155)/($G31-L$25)/(1+$G31)^$L$139)+$G$199)/$G$201 -> 98.493972
G32: =$G$73+2*$G$75 -> 0.10882145 | H32: =(SUM($H$109/(1+$G32)^$H$87,$I$109/(1+$G32)^$I$87,$J$109/(1+$G32)^$J$87,$K$109/(1+$G32)^$K$87,$L$109/(1+$G32)^$L$87)+SUM($H$134*(1-$H$129/$G$155)/(1+$G32)^$H$139,$I$134*(1-$I$129/$G$155)/(1+$G32)^$I$139,$J$134*(1-$J$129/$G$155)/(1+$G32)^$J$139,$K$134*(1-$K$129/$G$155)/(1+$G32)^$K$139,$L$134*(1-$L$129/$G$155)/(1+$G32)^$L$139)+($L$130*(1+H$25)*$G$153*(1-$G$154)*(1-H$25/$G$155)/($G32-H$25)/(1+$G32)^$L$139)+$G$199)/$G$201 -> 85.635496 | I32: =(SUM($H$109/(1+$G32)^$H$87,$I$109/(1+$G32)^$I$87,$J$109/(1+$G32)^$J$87,$K$109/(1+$G32)^$K$87,$L$109/(1+$G32)^$L$87)+SUM($H$134*(1-$H$129/$G$155)/(1+$G32)^$H$139,$I$134*(1-$I$129/$G$155)/(1+$G32)^$I$139,$J$134*(1-$J$129/$G$155)/(1+$G32)^$J$139,$K$134*(1-$K$129/$G$155)/(1+$G32)^$K$139,$L$134*(1-$L$129/$G$155)/(1+$G32)^$L$139)+($L$130*(1+I$25)*$G$153*(1-$G$154)*(1-I$25/$G$155)/($G32-I$25)/(1+$G32)^$L$139)+$G$199)/$G$201 -> 86.951744 | J32: =(SUM($H$109/(1+$G32)^$H$87,$I$109/(1+$G32)^$I$87,$J$109/(1+$G32)^$J$87,$K$109/(1+$G32)^$K$87,$L$109/(1+$G32)^$L$87)+SUM($H$134*(1-$H$129/$G$155)/(1+$G32)^$H$139,$I$134*(1-$I$129/$G$155)/(1+$G32)^$I$139,$J$134*(1-$J$129/$G$155)/(1+$G32)^$J$139,$K$134*(1-$K$129/$G$155)/(1+$G32)^$K$139,$L$134*(1-$L$129/$G$155)/(1+$G32)^$L$139)+($L$130*(1+J$25)*$G$153*(1-$G$154)*(1-J$25/$G$155)/($G32-J$25)/(1+$G32)^$L$139)+$G$199)/$G$201 -> 88.403734 | K32: =(SUM($H$109/(1+$G32)^$H$87,$I$109/(1+$G32)^$I$87,$J$109/(1+$G32)^$J$87,$K$109/(1+$G32)^$K$87,$L$109/(1+$G32)^$L$87)+SUM($H$134*(1-$H$129/$G$155)/(1+$G32)^$H$139,$I$134*(1-$I$129/$G$155)/(1+$G32)^$I$139,$J$134*(1-$J$129/$G$155)/(1+$G32)^$J$139,$K$134*(1-$K$129/$G$155)/(1+$G32)^$K$139,$L$134*(1-$L$129/$G$155)/(1+$G32)^$L$139)+($L$130*(1+K$25)*$G$153*(1-$G$154)*(1-K$25/$G$155)/($G32-K$25)/(1+$G32)^$L$139)+$G$199)/$G$201 -> 90.015758 | L32: =(SUM($H$109/(1+$G32)^$H$87,$I$109/(1+$G32)^$I$87,$J$109/(1+$G32)^$J$87,$K$109/(1+$G32)^$K$87,$L$109/(1+$G32)^$L$87)+SUM($H$134*(1-$H$129/$G$155)/(1+$G32)^$H$139,$I$134*(1-$I$129/$G$155)/(1+$G32)^$I$139,$J$134*(1-$J$129/$G$155)/(1+$G32)^$J$139,$K$134*(1-$K$129/$G$155)/(1+$G32)^$K$139,$L$134*(1-$L$129/$G$155)/(1+$G32)^$L$139)+($L$130*(1+L$25)*$G$153*(1-$G$154)*(1-L$25/$G$155)/($G32-L$25)/(1+$G32)^$L$139)+$G$199)/$G$201 -> 91.818269
G33: =$G$73+3*$G$75 -> 0.11382145 | H33: =(SUM($H$109/(1+$G33)^$H$87,$I$109/(1+$G33)^$I$87,$J$109/(1+$G33)^$J$87,$K$109/(1+$G33)^$K$87,$L$109/(1+$G33)^$L$87)+SUM($H$134*(1-$H$129/$G$155)/(1+$G33)^$H$139,$I$134*(1-$I$129/$G$155)/(1+$G33)^$I$139,$J$134*(1-$J$129/$G$155)/(1+$G33)^$J$139,$K$134*(1-$K$129/$G$155)/(1+$G33)^$K$139,$L$134*(1-$L$129/$G$155)/(1+$G33)^$L$139)+($L$130*(1+H$25)*$G$153*(1-$G$154)*(1-H$25/$G$155)/($G33-H$25)/(1+$G33)^$L$139)+$G$199)/$G$201 -> 80.83614 | I33: =(SUM($H$109/(1+$G33)^$H$87,$I$109/(1+$G33)^$I$87,$J$109/(1+$G33)^$J$87,$K$109/(1+$G33)^$K$87,$L$109/(1+$G33)^$L$87)+SUM($H$134*(1-$H$129/$G$155)/(1+$G33)^$H$139,$I$134*(1-$I$129/$G$155)/(1+$G33)^$I$139,$J$134*(1-$J$129/$G$155)/(1+$G33)^$J$139,$K$134*(1-$K$129/$G$155)/(1+$G33)^$K$139,$L$134*(1-$L$129/$G$155)/(1+$G33)^$L$139)+($L$130*(1+I$25)*$G$153*(1-$G$154)*(1-I$25/$G$155)/($G33-I$25)/(1+$G33)^$L$139)+$G$199)/$G$201 -> 81.933806 | J33: =(SUM($H$109/(1+$G33)^$H$87,$I$109/(1+$G33)^$I$87,$J$109/(1+$G33)^$J$87,$K$109/(1+$G33)^$K$87,$L$109/(1+$G33)^$L$87)+SUM($H$134*(1-$H$129/$G$155)/(1+$G33)^$H$139,$I$134*(1-$I$129/$G$155)/(1+$G33)^$I$139,$J$134*(1-$J$129/$G$155)/(1+$G33)^$J$139,$K$134*(1-$K$129/$G$155)/(1+$G33)^$K$139,$L$134*(1-$L$129/$G$155)/(1+$G33)^$L$139)+($L$130*(1+J$25)*$G$153*(1-$G$154)*(1-J$25/$G$155)/($G33-J$25)/(1+$G33)^$L$139)+$G$199)/$G$201 -> 83.13717 | K33: =(SUM($H$109/(1+$G33)^$H$87,$I$109/(1+$G33)^$I$87,$J$109/(1+$G33)^$J$87,$K$109/(1+$G33)^$K$87,$L$109/(1+$G33)^$L$87)+SUM($H$134*(1-$H$129/$G$155)/(1+$G33)^$H$139,$I$134*(1-$I$129/$G$155)/(1+$G33)^$I$139,$J$134*(1-$J$129/$G$155)/(1+$G33)^$J$139,$K$134*(1-$K$129/$G$155)/(1+$G33)^$K$139,$L$134*(1-$L$129/$G$155)/(1+$G33)^$L$139)+($L$130*(1+K$25)*$G$153*(1-$G$154)*(1-K$25/$G$155)/($G33-K$25)/(1+$G33)^$L$139)+$G$199)/$G$201 -> 84.464081 | L33: =(SUM($H$109/(1+$G33)^$H$87,$I$109/(1+$G33)^$I$87,$J$109/(1+$G33)^$J$87,$K$109/(1+$G33)^$K$87,$L$109/(1+$G33)^$L$87)+SUM($H$134*(1-$H$129/$G$155)/(1+$G33)^$H$139,$I$134*(1-$I$129/$G$155)/(1+$G33)^$I$139,$J$134*(1-$J$129/$G$155)/(1+$G33)^$J$139,$K$134*(1-$K$129/$G$155)/(1+$G33)^$K$139,$L$134*(1-$L$129/$G$155)/(1+$G33)^$L$139)+($L$130*(1+L$25)*$G$153*(1-$G$154)*(1-L$25/$G$155)/($G33-L$25)/(1+$G33)^$L$139)+$G$199)/$G$201 -> 85.936649
G34: =$G$73+4*$G$75 -> 0.11882145 | H34: =(SUM($H$109/(1+$G34)^$H$87,$I$109/(1+$G34)^$I$87,$J$109/(1+$G34)^$J$87,$K$109/(1+$G34)^$K$87,$L$109/(1+$G34)^$L$87)+SUM($H$134*(1-$H$129/$G$155)/(1+$G34)^$H$139,$I$134*(1-$I$129/$G$155)/(1+$G34)^$I$139,$J$134*(1-$J$129/$G$155)/(1+$G34)^$J$139,$K$134*(1-$K$129/$G$155)/(1+$G34)^$K$139,$L$134*(1-$L$129/$G$155)/(1+$G34)^$L$139)+($L$130*(1+H$25)*$G$153*(1-$G$154)*(1-H$25/$G$155)/($G34-H$25)/(1+$G34)^$L$139)+$G$199)/$G$201 -> 76.488614 | I34: =(SUM($H$109/(1+$G34)^$H$87,$I$109/(1+$G34)^$I$87,$J$109/(1+$G34)^$J$87,$K$109/(1+$G34)^$K$87,$L$109/(1+$G34)^$L$87)+SUM($H$134*(1-$H$129/$G$155)/(1+$G34)^$H$139,$I$134*(1-$I$129/$G$155)/(1+$G34)^$I$139,$J$134*(1-$J$129/$G$155)/(1+$G34)^$J$139,$K$134*(1-$K$129/$G$155)/(1+$G34)^$K$139,$L$134*(1-$L$129/$G$155)/(1+$G34)^$L$139)+($L$130*(1+I$25)*$G$153*(1-$G$154)*(1-I$25/$G$155)/($G34-I$25)/(1+$G34)^$L$139)+$G$199)/$G$201 -> 77.407267 | J34: =(SUM($H$109/(1+$G34)^$H$87,$I$109/(1+$G34)^$I$87,$J$109/(1+$G34)^$J$87,$K$109/(1+$G34)^$K$87,$L$109/(1+$G34)^$L$87)+SUM($H$134*(1-$H$129/$G$155)/(1+$G34)^$H$139,$I$134*(1-$I$129/$G$155)/(1+$G34)^$I$139,$J$134*(1-$J$129/$G$155)/(1+$G34)^$J$139,$K$134*(1-$K$129/$G$155)/(1+$G34)^$K$139,$L$134*(1-$L$129/$G$155)/(1+$G34)^$L$139)+($L$130*(1+J$25)*$G$153*(1-$G$154)*(1-J$25/$G$155)/($G34-J$25)/(1+$G34)^$L$139)+$G$199)/$G$201 -> 78.408596 | K34: =(SUM($H$109/(1+$G34)^$H$87,$I$109/(1+$G34)^$I$87,$J$109/(1+$G34)^$J$87,$K$109/(1+$G34)^$K$87,$L$109/(1+$G34)^$L$87)+SUM($H$134*(1-$H$129/$G$155)/(1+$G34)^$H$139,$I$134*(1-$I$129/$G$155)/(1+$G34)^$I$139,$J$134*(1-$J$129/$G$155)/(1+$G34)^$J$139,$K$134*(1-$K$129/$G$155)/(1+$G34)^$K$139,$L$134*(1-$L$129/$G$155)/(1+$G34)^$L$139)+($L$130*(1+K$25)*$G$153*(1-$G$154)*(1-K$25/$G$155)/($G34-K$25)/(1+$G34)^$L$139)+$G$199)/$G$201 -> 79.505819 | L34: =(SUM($H$109/(1+$G34)^$H$87,$I$109/(1+$G34)^$I$87,$J$109/(1+$G34)^$J$87,$K$109/(1+$G34)^$K$87,$L$109/(1+$G34)^$L$87)+SUM($H$134*(1-$H$129/$G$155)/(1+$G34)^$H$139,$I$134*(1-$I$129/$G$155)/(1+$G34)^$I$139,$J$134*(1-$J$129/$G$155)/(1+$G34)^$J$139,$K$134*(1-$K$129/$G$155)/(1+$G34)^$K$139,$L$134*(1-$L$129/$G$155)/(1+$G34)^$L$139)+($L$130*(1+L$25)*$G$153*(1-$G$154)*(1-L$25/$G$155)/($G34-L$25)/(1+$G34)^$L$139)+$G$199)/$G$201 -> 80.715132
C36: No Excel What-If Data Table or captured results. All grid cells calculate dynamically from the explicit, transition and terminal cash flows.
C38: Mature incremental ROIC comparison
C40: Return on new capital | H40: 0.15 | I40: =G155 -> 0.2 | J40: 0.25
C41: Indicative value / diluted share | H41: =(SUM($H$109/(1+$G$74)^$H$87,$I$109/(1+$G$74)^$I$87,$J$109/(1+$G$74)^$J$87,$K$109/(1+$G$74)^$K$87,$L$109/(1+$G$74)^$L$87)+SUM($H$134*(1-$H$129/H$40)/(1+$G$74)^$H$139,$I$134*(1-$I$129/H$40)/(1+$G$74)^$I$139,$J$134*(1-$J$129/H$40)/(1+$G$74)^$J$139,$K$134*(1-$K$129/H$40)/(1+$G$74)^$K$139,$L$134*(1-$L$129/H$40)/(1+$G$74)^$L$139)+($L$130*(1+$G$156)*$G$153*(1-$G$154)*(1-$G$156/H$40)/($G$74-$G$156)/(1+$G$74)^$L$139)+$G$199)/$G$201 -> 97.463697 | I41: =(SUM($H$109/(1+$G$74)^$H$87,$I$109/(1+$G$74)^$I$87,$J$109/(1+$G$74)^$J$87,$K$109/(1+$G$74)^$K$87,$L$109/(1+$G$74)^$L$87)+SUM($H$134*(1-$H$129/I$40)/(1+$G$74)^$H$139,$I$134*(1-$I$129/I$40)/(1+$G$74)^$I$139,$J$134*(1-$J$129/I$40)/(1+$G$74)^$J$139,$K$134*(1-$K$129/I$40)/(1+$G$74)^$K$139,$L$134*(1-$L$129/I$40)/(1+$G$74)^$L$139)+($L$130*(1+$G$156)*$G$153*(1-$G$154)*(1-$G$156/I$40)/($G$74-$G$156)/(1+$G$74)^$L$139)+$G$199)/$G$201 -> 100.96145 | J41: =(SUM($H$109/(1+$G$74)^$H$87,$I$109/(1+$G$74)^$I$87,$J$109/(1+$G$74)^$J$87,$K$109/(1+$G$74)^$K$87,$L$109/(1+$G$74)^$L$87)+SUM($H$134*(1-$H$129/J$40)/(1+$G$74)^$H$139,$I$134*(1-$I$129/J$40)/(1+$G$74)^$I$139,$J$134*(1-$J$129/J$40)/(1+$G$74)^$J$139,$K$134*(1-$K$129/J$40)/(1+$G$74)^$K$139,$L$134*(1-$L$129/J$40)/(1+$G$74)^$L$139)+($L$130*(1+$G$156)*$G$153*(1-$G$154)*(1-$G$156/J$40)/($G$74-$G$156)/(1+$G$74)^$L$139)+$G$199)/$G$201 -> 103.06009
C42: Scenario | H42: Lower return | I42: Base case | J42: Higher return
C44: ROIC comparison changes reinvestment in both the transition and terminal periods. It does not change the operating forecasts or the EV-to-equity bridge.
C48: Market inputs, share count and WACC
C49: Valuation / quote date | G49: 46272
C50: Latest reported balance-sheet date | G50: 46053
C51: Observed price (pence) | G51: 15500 | H51: V01. Latest completed-session observation; not a live quote.
C52: Observed price (£) | G52: =G51/G78 -> 155 | H52: Convert pence into pounds before calculating market equity.
C53: Issued ordinary shares (m) | G53: 119.65681 | H53: V02. At 28 Aug 2026; announced 1 Sep. No treasury shares.
C54: ESOT shares excluded (m) | G54: 5.50476 | H54: V03, note 27. 31 Jan 2026 holding used as a dated proxy.
C55: Treasury shares excluded (m) | G55: 0 | H55: V02. ESOT holdings are separate from treasury shares.
C56: Current basic shares proxy (m) | G56: =G53-G54-G55 -> 114.15205 | H56: Issued less ESOT and treasury; not weighted-average EPS shares.
C57: Incremental dilution proxy (m) | G57: 2.3 | H57: V03, note 9: FY2026 weighted-average potential shares. Not a current option valuation.
C58: Diluted shares proxy (m) | G58: =G56+G57 -> 116.45205 | H58: Current issued count plus dated dilution inputs; refresh with interim details.
C59: Market value of equity | G59: =G52*G56 -> 17693.568 | H59: Basic economic shares for WACC weights, not DCF-implied equity.
C60: GBP risk-free rate (annual effective) | G60: =EXP(G351)-1 -> 0.053138306 | H60: V04. BoE 7 Sep 2026 ten-year nominal spot; continuous rate converted to annual effective.
C61: Mature-market implied ERP | G61: 0.0414 | H61: V05. Damodaran, 1 Sep 2026; US implied premium before default adjustment.
C62: ERP default-risk adjustment | G62: 0.0022 | H62: V05. Add the US default spread for a default-adjusted mature-market ERP.
C63: Applied equity risk premium | G63: =G61+G62 -> 0.0436 | H63: Mature-market proxy applied in GBP; no separate country-risk overlay.
C64: Triangulated equity beta | G64: 1.1 | H64: V09. Independent judgement: five-year vendor estimate c.1.04; European specialty-retail screen c.1.14.
C65: Cost of equity — CAPM | G65: =G60+G64*G63 -> 0.10109831 | H65: Risk-free rate + beta × equity risk premium.
C66: Assumed marginal credit spread | G66: 0.0111 | H66: V10. BBB spread proxy, January 2026 ratings basket; not an observed current NEXT bond spread.
C67: Pre-tax marginal cost of debt | G67: =G60+G66 -> 0.064238306 | H67: Not the historical coupon or the operating forecast refinancing rate.
C68: Marginal tax rate | G68: ='01 Assumptions'!H42 -> 0.25 | H68: 25% UK / forecast proxy; assume interest tax relief is usable.
C69: After-tax cost of debt | G69: =G67*(1-G68) -> 0.04817873 | H69: Interest tax shield is captured here, not deducted from FCFF.
C70: Estimated market value of financial debt | G70: =G354+G356+G357+SUM(L361:L367) -> 795.49021 | H70: Visible bond cash-flow valuation below. Leases excluded; bridge retains its approved carrying-value proxy.
C71: Equity weight | G71: =G59/SUM(G59,G70) -> 0.95697508 | H71: Market equity / (market equity + gross debt).
C72: Debt weight | G72: =G70/SUM(G59,G70) -> 0.043024918 | H72: Do not use net debt or lease debt in this operating-lease WACC.
C73: Calculated WACC | G73: =G65*G71+G69*G72 -> 0.098821446 | H73: Weighted opportunity cost to financial capital providers.
C74: Active base-case WACC | G74: =G73 -> 0.098821446 | H74: Base WACC links to its component calculation; formula sensitivities do not overwrite this input.
C75: WACC sensitivity increment | G75: 0.005 | H75: Independent range setting: ±2.0 percentage points in 0.5-point steps.
C76: Terminal-growth sensitivity increment | G76: 0.005 | H76: Independent range setting: 1.0%–3.0% around 2.0%.
C77: Day-count basis | G77: 365 | H77: Actual days / 365 for discount exponents.
C78: Pence per pound | G78: 100 | H78: Unit conversion constant.
C79: FY2027 remaining-flow allocation adjustment | G79: 0 | H79: Zero = time-proportion proxy. A 10pp shift is tested separately; not monthly seasonality data.
C82: FCFF from the existing operating model
H84: ='02 Model'!H6 -> FY2027E | I84: ='02 Model'!I6 -> FY2028E | J84: ='02 Model'!J6 -> FY2029E | K84: ='02 Model'!K6 -> FY2030E | L84: ='02 Model'!L6 -> FY2031E
C85: Fiscal year end | H85: 46417 | I85: 46781 | J85: 47145 | K85: 47509 | L85: 47873
C86: Remaining share of annual FCFF | H86: =MAX(0,MIN(1,(H85-$G$49)/(H85-$G$50)+$G$79)) -> 0.39835165 | I86: =MAX(0,MIN(1,(I85-$G$49)/(I85-H85))) -> 1 | J86: =MAX(0,MIN(1,(J85-$G$49)/(J85-I85))) -> 1 | K86: =MAX(0,MIN(1,(K85-$G$49)/(K85-J85))) -> 1 | L86: =MAX(0,MIN(1,(L85-$G$49)/(L85-K85))) -> 1
C87: Time to fiscal year end (years) | H87: =MAX(0,(H85-$G$49)/$G$77) -> 0.39726027 | I87: =MAX(0,(I85-$G$49)/$G$77) -> 1.3945205 | J87: =MAX(0,(J85-$G$49)/$G$77) -> 2.3917808 | K87: =MAX(0,(K85-$G$49)/$G$77) -> 3.3890411 | L87: =MAX(0,(L85-$G$49)/$G$77) -> 4.3863014
C88: Revenue | H88: ='02 Model'!H8 -> 7265.621 | I88: ='02 Model'!I8 -> 7701.5583 | J88: ='02 Model'!J8 -> 8125.144 | K88: ='02 Model'!K8 -> 8531.4012 | L88: ='02 Model'!L8 -> 8915.3142
C89: Statutory operating profit | H89: ='02 Model'!H24 -> 1332.1399 | I89: ='02 Model'!I24 -> 1419.9898 | J89: ='02 Model'!J24 -> 1502.3393 | K89: ='02 Model'!K24 -> 1577.6063 | L89: ='02 Model'!L24 -> 1653.1638
C90: Remove equity-accounted associate results | H90: =-SUM('02 Model'!H21:H22) -> -8 | I90: =-SUM('02 Model'!I21:I22) -> -8.5 | J90: =-SUM('02 Model'!J21:J22) -> -9 | K90: =-SUM('02 Model'!K21:K22) -> -9.5 | L90: =-SUM('02 Model'!L21:L22) -> -10
C91: Reverse ROU depreciation | H91: =-'03 Schedules'!H72 -> 156 | I91: =-'03 Schedules'!I72 -> 158 | J91: =-'03 Schedules'!J72 -> 160 | K91: =-'03 Schedules'!K72 -> 162 | L91: =-'03 Schedules'!L72 -> 164
C92: Deduct full lease cash payments | H92: ='03 Schedules'!H82+'02 Model'!H121 -> -225 | I92: ='03 Schedules'!I82+'02 Model'!I121 -> -230 | J92: ='03 Schedules'!J82+'02 Model'!J121 -> -235 | K92: ='03 Schedules'!K82+'02 Model'!K121 -> -240 | L92: ='03 Schedules'!L82+'02 Model'!L121 -> -245
C93: Lease-adjusted consolidated EBIT | H93: =SUM(H89:H92) -> 1255.1399 | I93: =SUM(I89:I92) -> 1339.4898 | J93: =SUM(J89:J92) -> 1418.3393 | K93: =SUM(K89:K92) -> 1490.1063 | L93: =SUM(L89:L92) -> 1562.1638
C94: Operating cash-tax proxy rate | H94: ='01 Assumptions'!H42 -> 0.25 | I94: ='01 Assumptions'!I42 -> 0.25 | J94: ='01 Assumptions'!J42 -> 0.25 | K94: ='01 Assumptions'!K42 -> 0.25 | L94: ='01 Assumptions'!L42 -> 0.25
C95: Cash taxes on operating profit | H95: =-H93*H94 -> -313.78497 | I95: =-I93*I94 -> -334.87246 | J95: =-J93*J94 -> -354.58484 | K95: =-K93*K94 -> -372.52658 | L95: =-L93*L94 -> -390.54094
C96: NOPAT | H96: =SUM(H93,H95) -> 941.35491 | I96: =SUM(I93,I95) -> 1004.6174 | J96: =SUM(J93,J95) -> 1063.7545 | K96: =SUM(K93,K95) -> 1117.5797 | L96: =SUM(L93,L95) -> 1171.6228
C97: PP&E D&A / non-cash asset adjustments | H97: ='03 Schedules'!H348 -> 120 | I97: ='03 Schedules'!I348 -> 128 | J97: ='03 Schedules'!J348 -> 140 | K97: ='03 Schedules'!K348 -> 155 | L97: ='03 Schedules'!L348 -> 170
C98: Intangible D&A / non-cash asset adjustments | H98: ='03 Schedules'!H351 -> 58 | I98: ='03 Schedules'!I351 -> 60 | J98: ='03 Schedules'!J351 -> 62 | K98: ='03 Schedules'!K351 -> 64 | L98: ='03 Schedules'!L351 -> 66
C99: Other asset non-cash adjustment | H99: ='03 Schedules'!H349 -> 0 | I99: ='03 Schedules'!I349 -> 0 | J99: ='03 Schedules'!J349 -> 0 | K99: ='03 Schedules'!K349 -> 0 | L99: ='03 Schedules'!L349 -> 0
C100: Cash capex, net of asset sale proceeds | H100: =SUM('02 Model'!H102:H106) -> -237 | I100: =SUM('02 Model'!I102:I106) -> -252 | J100: =SUM('02 Model'!J102:J106) -> -227 | K100: =SUM('02 Model'!K102:K106) -> -289 | L100: =SUM('02 Model'!L102:L106) -> -300
C101: Inventories and return assets | H101: =SUM('02 Model'!H46,'02 Model'!H48) -> 989.55631 | I101: =SUM('02 Model'!I46,'02 Model'!I48) -> 1101.5526 | J101: =SUM('02 Model'!J46,'02 Model'!J48) -> 1108.7661 | K101: =SUM('02 Model'!K46,'02 Model'!K48) -> 1216.5888 | L101: =SUM('02 Model'!L46,'02 Model'!L48) -> 1214.0771
C102: Customer and operating receivables | H102: ='02 Model'!H47-'03 Schedules'!H117 -> 1627.9218 | I102: ='02 Model'!I47-'03 Schedules'!I117 -> 1671.7371 | J102: ='02 Model'!J47-'03 Schedules'!J117 -> 1716.957 | K102: ='02 Model'!K47-'03 Schedules'!K117 -> 1761.5374 | L102: ='02 Model'!L47-'03 Schedules'!L117 -> 1805.4343
C103: Operating payables (negative) | H103: =SUM('02 Model'!H59,'02 Model'!H70) -> -1243.7083 | I103: =SUM('02 Model'!I59,'02 Model'!I70) -> -1286.752 | J103: =SUM('02 Model'!J59,'02 Model'!J70) -> -1382.15 | K103: =SUM('02 Model'!K59,'02 Model'!K70) -> -1420.6835 | L103: =SUM('02 Model'!L59,'02 Model'!L70) -> -1508.4618
C104: Required operating cash | H104: =$G$183 -> 100 | I104: =$G$183 -> 100 | J104: =$G$183 -> 100 | K104: =$G$183 -> 100 | L104: =$G$183 -> 100
C105: Operating net working capital | H105: =SUM(H101:H104) -> 1473.7699 | I105: =SUM(I101:I104) -> 1586.5378 | J105: =SUM(J101:J104) -> 1543.5732 | K105: =SUM(K101:K104) -> 1657.4428 | L105: =SUM(L101:L104) -> 1611.0496
C106: Opening operating net working capital | H106: =SUM('02 Model'!G46:G48,'02 Model'!G59,'02 Model'!G70)-'03 Schedules'!G117+H104 -> 1569.9 | I106: =H105 -> 1473.7699 | J106: =I105 -> 1586.5378 | K106: =J105 -> 1543.5732 | L106: =K105 -> 1657.4428
C107: Increase / (decrease) in operating NWC | H107: =H105-H106 -> -96.130136 | I107: =I105-I106 -> 112.76792 | J107: =J105-J106 -> -42.964612 | K107: =K105-K106 -> 113.86958 | L107: =L105-L106 -> -46.393113
C108: FCFF — full fiscal year | H108: =SUM(H96:H100)-H107 -> 978.48505 | I108: =SUM(I96:I100)-I107 -> 827.84946 | J108: =SUM(J96:J100)-J107 -> 1081.7191 | K108: =SUM(K96:K100)-K107 -> 933.71016 | L108: =SUM(L96:L100)-L107 -> 1154.0159
C109: FCFF included after valuation date | H109: =H108*H86 -> 389.78113 | I109: =I108*I86 -> 827.84946 | J109: =J108*J86 -> 1081.7191 | K109: =K108*K86 -> 933.71016 | L109: =L108*L86 -> 1154.0159
C110: Discount factor — year-end convention | H110: =1/(1+$G$74)^H87 -> 0.96325501 | I110: =1/(1+$G$74)^I87 -> 0.87685197 | J110: =1/(1+$G$74)^J87 -> 0.79819919 | K110: =1/(1+$G$74)^K87 -> 0.72660149 | L110: =1/(1+$G$74)^L87 -> 0.66142604
C111: Present value of explicit FCFF | H111: =H109*H110 -> 375.45863 | I111: =I109*I110 -> 725.90143 | J111: =J109*J110 -> 863.42733 | K111: =K109*K110 -> 678.43519 | L111: =L109*L110 -> 763.29618
C113: SBC retained as an economic expense | H113: ='03 Schedules'!H353 -> 45 | I113: ='03 Schedules'!I353 -> 47 | J113: ='03 Schedules'!J353 -> 49 | K113: ='03 Schedules'!K353 -> 51 | L113: ='03 Schedules'!L353 -> 53
C114: Interest income excluded from FCFF | H114: ='03 Schedules'!H355 -> 5.367 | I114: ='03 Schedules'!I355 -> 5.731815 | J114: ='03 Schedules'!J355 -> 5.2 | K114: ='03 Schedules'!K355 -> 5.3 | L114: ='03 Schedules'!L355 -> 5.4
C115: NCI net profit included in consolidation | H115: ='02 Model'!H30-'03 Schedules'!H242 -> 10.295414 | I115: ='02 Model'!I30-'03 Schedules'!I242 -> 11.08422 | J115: ='02 Model'!J30-'03 Schedules'!J242 -> 11.773191 | K115: ='02 Model'!K30-'03 Schedules'!K242 -> 12.410837 | L115: ='02 Model'!L30-'03 Schedules'!L242 -> 13.050578
C116: FCFF / revenue | H116: =H108/H88 -> 0.13467329 | I116: =I108/I88 -> 0.10749116 | J116: =J108/J88 -> 0.1331323 | K116: =K108/K88 -> 0.10944394 | L116: =L108/L88 -> 0.12944198
C117: Operating EBIT margin after lease cash cost | H117: =H93/H88 -> 0.17275053 | I117: =I93/I88 -> 0.17392452 | J117: =J93/J88 -> 0.17456175 | K117: =K93/K88 -> 0.17466138 | L117: =L93/L88 -> 0.17522251
...
